<?xml version="1.0" encoding="utf-8" standalone="no"?>
<list xmlns:xsi="http://www.w3.org/2001/XMLSchema-instance" xsi:noNamespaceSchemaLocation="../../../xsd/OptionData.xsd">
	<optionData id="27000">
		<for>

			<add order="0x60" stat="pCritRate" val="30.8"/>
		</for>
	</optionData>
	<optionData id="27001">
		<for>

			<add order="0x60" stat="pDef" val="23.57"/>
			<add order="0x60" stat="mDef" val="21.335"/>
		</for>
	</optionData>
	<optionData id="27002">
		<for>

			<add order="0x60" stat="pDef" val="23.57"/>
			<add order="0x60" stat="maxHp" val="60.975"/>
		</for>
	</optionData>
	<optionData id="27003">
		<for>

			<add order="0x60" stat="pDef" val="23.57"/>
			<add order="0x60" stat="maxMp" val="26.885"/>
		</for>
	</optionData>
	<optionData id="27004">
		<for>

			<add order="0x60" stat="pDef" val="23.57"/>
			<add order="0x60" stat="maxCp" val="120.045"/>
		</for>
	</optionData>
	<optionData id="27005">
		<for>

			<add order="0x60" stat="pDef" val="23.57"/>
			<add order="0x60" stat="pAtk" val="26.465"/>
		</for>
	</optionData>
	<optionData id="27006">
		<for>

			<add order="0x60" stat="pDef" val="23.57"/>
			<add order="0x60" stat="mAtk" val="33.305"/>
		</for>
	</optionData>
	<optionData id="27007">
		<for>

			<add order="0x60" stat="pDef" val="23.57"/>
			<add order="0x60" stat="regHp" val="0.235"/>
		</for>
	</optionData>
	<optionData id="27008">
		<for>

			<add order="0x60" stat="pDef" val="23.57"/>
			<add order="0x60" stat="regMp" val="0.1"/>
		</for>
	</optionData>
	<optionData id="27009">
		<for>

			<add order="0x60" stat="pDef" val="23.57"/>
			<add order="0x60" stat="regCp" val="0.235"/>
		</for>
	</optionData>
	<optionData id="27010">
		<for>

			<add order="0x60" stat="pDef" val="23.57"/>
			<add order="0x60" stat="ratePhysicalEvas" val="1.4105"/>
		</for>
	</optionData>
	<optionData id="27011">
		<for>

			<add order="0x60" stat="pDef" val="23.57"/>
			<add order="0x60" stat="accPhysical" val="2.0565"/>
		</for>
	</optionData>
	<optionData id="27012">
		<for>

			<add order="0x60" stat="pDef" val="23.57"/>
			<add order="0x60" stat="pCritRate" val="15.4"/>
		</for>
	</optionData>
	<optionData id="27013">
		<for>

			<add order="0x60" stat="mDef" val="21.335"/>
			<add order="0x60" stat="maxHp" val="60.975"/>
		</for>
	</optionData>
	<optionData id="27014">
		<for>

			<add order="0x60" stat="mDef" val="21.335"/>
			<add order="0x60" stat="maxMp" val="26.885"/>
		</for>
	</optionData>
	<optionData id="27015">
		<for>

			<add order="0x60" stat="mDef" val="21.335"/>
			<add order="0x60" stat="maxCp" val="120.045"/>
		</for>
	</optionData>
	<optionData id="27016">
		<for>

			<add order="0x60" stat="mDef" val="21.335"/>
			<add order="0x60" stat="pAtk" val="26.465"/>
		</for>
	</optionData>
	<optionData id="27017">
		<for>

			<add order="0x60" stat="mDef" val="21.335"/>
			<add order="0x60" stat="mAtk" val="33.305"/>
		</for>
	</optionData>
	<optionData id="27018">
		<for>

			<add order="0x60" stat="mDef" val="21.335"/>
			<add order="0x60" stat="regHp" val="0.235"/>
		</for>
	</optionData>
	<optionData id="27019">
		<for>

			<add order="0x60" stat="mDef" val="21.335"/>
			<add order="0x60" stat="regMp" val="0.1"/>
		</for>
	</optionData>
	<optionData id="27020">
		<for>

			<add order="0x60" stat="mDef" val="21.335"/>
			<add order="0x60" stat="regCp" val="0.235"/>
		</for>
	</optionData>
	<optionData id="27021">
		<for>

			<add order="0x60" stat="mDef" val="21.335"/>
			<add order="0x60" stat="ratePhysicalEvas" val="1.4105"/>
		</for>
	</optionData>
	<optionData id="27022">
		<for>

			<add order="0x60" stat="mDef" val="21.335"/>
			<add order="0x60" stat="accPhysical" val="2.0565"/>
		</for>
	</optionData>
	<optionData id="27023">
		<for>

			<add order="0x60" stat="mDef" val="21.335"/>
			<add order="0x60" stat="pCritRate" val="15.4"/>
		</for>
	</optionData>
	<optionData id="27024">
		<for>

			<add order="0x60" stat="maxHp" val="60.975"/>
			<add order="0x60" stat="maxMp" val="26.885"/>
		</for>
	</optionData>
	<optionData id="27025">
		<for>

			<add order="0x60" stat="maxHp" val="60.975"/>
			<add order="0x60" stat="maxCp" val="120.045"/>
		</for>
	</optionData>
	<optionData id="27026">
		<for>

			<add order="0x60" stat="maxHp" val="60.975"/>
			<add order="0x60" stat="pAtk" val="26.465"/>
		</for>
	</optionData>
	<optionData id="27027">
		<for>

			<add order="0x60" stat="maxHp" val="60.975"/>
			<add order="0x60" stat="mAtk" val="33.305"/>
		</for>
	</optionData>
	<optionData id="27028">
		<for>

			<add order="0x60" stat="maxHp" val="60.975"/>
			<add order="0x60" stat="regHp" val="0.235"/>
		</for>
	</optionData>
	<optionData id="27029">
		<for>

			<add order="0x60" stat="maxHp" val="60.975"/>
			<add order="0x60" stat="regMp" val="0.1"/>
		</for>
	</optionData>
	<optionData id="27030">
		<for>

			<add order="0x60" stat="maxHp" val="60.975"/>
			<add order="0x60" stat="regCp" val="0.235"/>
		</for>
	</optionData>
	<optionData id="27031">
		<for>

			<add order="0x60" stat="maxHp" val="60.975"/>
			<add order="0x60" stat="ratePhysicalEvas" val="1.4105"/>
		</for>
	</optionData>
	<optionData id="27032">
		<for>

			<add order="0x60" stat="maxHp" val="60.975"/>
			<add order="0x60" stat="accPhysical" val="2.0565"/>
		</for>
	</optionData>
	<optionData id="27033">
		<for>

			<add order="0x60" stat="maxHp" val="60.975"/>
			<add order="0x60" stat="pCritRate" val="15.4"/>
		</for>
	</optionData>
	<optionData id="27034">
		<for>

			<add order="0x60" stat="maxMp" val="26.885"/>
			<add order="0x60" stat="maxCp" val="120.045"/>
		</for>
	</optionData>
	<optionData id="27035">
		<for>

			<add order="0x60" stat="maxMp" val="26.885"/>
			<add order="0x60" stat="pAtk" val="26.465"/>
		</for>
	</optionData>
	<optionData id="27036">
		<for>

			<add order="0x60" stat="maxMp" val="26.885"/>
			<add order="0x60" stat="mAtk" val="33.305"/>
		</for>
	</optionData>
	<optionData id="27037">
		<for>

			<add order="0x60" stat="maxMp" val="26.885"/>
			<add order="0x60" stat="regHp" val="0.235"/>
		</for>
	</optionData>
	<optionData id="27038">
		<for>

			<add order="0x60" stat="maxMp" val="26.885"/>
			<add order="0x60" stat="regMp" val="0.1"/>
		</for>
	</optionData>
	<optionData id="27039">
		<for>

			<add order="0x60" stat="maxMp" val="26.885"/>
			<add order="0x60" stat="regCp" val="0.235"/>
		</for>
	</optionData>
	<optionData id="27040">
		<for>

			<add order="0x60" stat="maxMp" val="26.885"/>
			<add order="0x60" stat="ratePhysicalEvas" val="1.4105"/>
		</for>
	</optionData>
	<optionData id="27041">
		<for>

			<add order="0x60" stat="maxMp" val="26.885"/>
			<add order="0x60" stat="accPhysical" val="2.0565"/>
		</for>
	</optionData>
	<optionData id="27042">
		<for>

			<add order="0x60" stat="maxMp" val="26.885"/>
			<add order="0x60" stat="pCritRate" val="15.4"/>
		</for>
	</optionData>
	<optionData id="27043">
		<for>

			<add order="0x60" stat="maxCp" val="120.045"/>
			<add order="0x60" stat="pAtk" val="26.465"/>
		</for>
	</optionData>
	<optionData id="27044">
		<for>

			<add order="0x60" stat="maxCp" val="120.045"/>
			<add order="0x60" stat="mAtk" val="33.305"/>
		</for>
	</optionData>
	<optionData id="27045">
		<for>

			<add order="0x60" stat="maxCp" val="120.045"/>
			<add order="0x60" stat="regHp" val="0.235"/>
		</for>
	</optionData>
	<optionData id="27046">
		<for>

			<add order="0x60" stat="maxCp" val="120.045"/>
			<add order="0x60" stat="regMp" val="0.1"/>
		</for>
	</optionData>
	<optionData id="27047">
		<for>

			<add order="0x60" stat="maxCp" val="120.045"/>
			<add order="0x60" stat="regCp" val="0.235"/>
		</for>
	</optionData>
	<optionData id="27048">
		<for>

			<add order="0x60" stat="maxCp" val="120.045"/>
			<add order="0x60" stat="ratePhysicalEvas" val="1.4105"/>
		</for>
	</optionData>
	<optionData id="27049">
		<for>

			<add order="0x60" stat="maxCp" val="120.045"/>
			<add order="0x60" stat="accPhysical" val="2.0565"/>
		</for>
	</optionData>
	<optionData id="27050">
		<for>

			<add order="0x60" stat="maxCp" val="120.045"/>
			<add order="0x60" stat="pCritRate" val="15.4"/>
		</for>
	</optionData>
	<optionData id="27051">
		<for>

			<add order="0x60" stat="pAtk" val="26.465"/>
			<add order="0x60" stat="mAtk" val="33.305"/>
		</for>
	</optionData>
	<optionData id="27052">
		<for>

			<add order="0x60" stat="pAtk" val="26.465"/>
			<add order="0x60" stat="regHp" val="0.235"/>
		</for>
	</optionData>
	<optionData id="27053">
		<for>

			<add order="0x60" stat="pAtk" val="26.465"/>
			<add order="0x60" stat="regMp" val="0.1"/>
		</for>
	</optionData>
	<optionData id="27054">
		<for>

			<add order="0x60" stat="pAtk" val="26.465"/>
			<add order="0x60" stat="regCp" val="0.235"/>
		</for>
	</optionData>
	<optionData id="27055">
		<for>

			<add order="0x60" stat="pAtk" val="26.465"/>
			<add order="0x60" stat="ratePhysicalEvas" val="1.4105"/>
		</for>
	</optionData>
	<optionData id="27056">
		<for>

			<add order="0x60" stat="pAtk" val="26.465"/>
			<add order="0x60" stat="accPhysical" val="2.0565"/>
		</for>
	</optionData>
	<optionData id="27057">
		<for>

			<add order="0x60" stat="pAtk" val="26.465"/>
			<add order="0x60" stat="pCritRate" val="15.4"/>
		</for>
	</optionData>
	<optionData id="27058">
		<for>

			<add order="0x60" stat="mAtk" val="33.305"/>
			<add order="0x60" stat="regHp" val="0.235"/>
		</for>
	</optionData>
	<optionData id="27059">
		<for>

			<add order="0x60" stat="mAtk" val="33.305"/>
			<add order="0x60" stat="regMp" val="0.1"/>
		</for>
	</optionData>
	<optionData id="27060">
		<for>

			<add order="0x60" stat="mAtk" val="33.305"/>
			<add order="0x60" stat="regCp" val="0.235"/>
		</for>
	</optionData>
	<optionData id="27061">
		<for>

			<add order="0x60" stat="mAtk" val="33.305"/>
			<add order="0x60" stat="ratePhysicalEvas" val="1.4105"/>
		</for>
	</optionData>
	<optionData id="27062">
		<for>

			<add order="0x60" stat="mAtk" val="33.305"/>
			<add order="0x60" stat="accPhysical" val="2.0565"/>
		</for>
	</optionData>
	<optionData id="27063">
		<for>

			<add order="0x60" stat="mAtk" val="33.305"/>
			<add order="0x60" stat="pCritRate" val="15.4"/>
		</for>
	</optionData>
	<optionData id="27064">
		<for>

			<add order="0x60" stat="regHp" val="0.235"/>
			<add order="0x60" stat="regMp" val="0.1"/>
		</for>
	</optionData>
	<optionData id="27065">
		<for>

			<add order="0x60" stat="regHp" val="0.235"/>
			<add order="0x60" stat="regCp" val="0.235"/>
		</for>
	</optionData>
	<optionData id="27066">
		<for>

			<add order="0x60" stat="regHp" val="0.235"/>
			<add order="0x60" stat="ratePhysicalEvas" val="1.4105"/>
		</for>
	</optionData>
	<optionData id="27067">
		<for>

			<add order="0x60" stat="regHp" val="0.235"/>
			<add order="0x60" stat="accPhysical" val="2.0565"/>
		</for>
	</optionData>
	<optionData id="27068">
		<for>

			<add order="0x60" stat="regHp" val="0.235"/>
			<add order="0x60" stat="pCritRate" val="15.4"/>
		</for>
	</optionData>
	<optionData id="27069">
		<for>

			<add order="0x60" stat="regMp" val="0.1"/>
			<add order="0x60" stat="regCp" val="0.235"/>
		</for>
	</optionData>
	<optionData id="27070">
		<for>

			<add order="0x60" stat="regMp" val="0.1"/>
			<add order="0x60" stat="ratePhysicalEvas" val="1.4105"/>
		</for>
	</optionData>
	<optionData id="27071">
		<for>

			<add order="0x60" stat="regMp" val="0.1"/>
			<add order="0x60" stat="accPhysical" val="2.0565"/>
		</for>
	</optionData>
	<optionData id="27072">
		<for>

			<add order="0x60" stat="regMp" val="0.1"/>
			<add order="0x60" stat="pCritRate" val="15.4"/>
		</for>
	</optionData>
	<optionData id="27073">
		<for>

			<add order="0x60" stat="regCp" val="0.235"/>
			<add order="0x60" stat="ratePhysicalEvas" val="1.4105"/>
		</for>
	</optionData>
	<optionData id="27074">
		<for>

			<add order="0x60" stat="regCp" val="0.235"/>
			<add order="0x60" stat="accPhysical" val="2.0565"/>
		</for>
	</optionData>
	<optionData id="27075">
		<for>

			<add order="0x60" stat="regCp" val="0.235"/>
			<add order="0x60" stat="pCritRate" val="15.4"/>
		</for>
	</optionData>
	<optionData id="27076">
		<for>

			<add order="0x60" stat="ratePhysicalEvas" val="1.4105"/>
			<add order="0x60" stat="accPhysical" val="2.0565"/>
		</for>
	</optionData>
	<optionData id="27077">
		<for>

			<add order="0x60" stat="ratePhysicalEvas" val="1.4105"/>
			<add order="0x60" stat="pCritRate" val="15.4"/>
		</for>
	</optionData>
	<optionData id="27078">
		<for>

			<add order="0x60" stat="accPhysical" val="2.0565"/>
			<add order="0x60" stat="pCritRate" val="15.4"/>
		</for>
	</optionData>
	<optionData id="27079">
		<for>

			<add order="0x60" stat="pDef" val="52.14"/>
		</for>
	</optionData>
	<optionData id="27080">
		<for>

			<add order="0x60" stat="mDef" val="48.13"/>
		</for>
	</optionData>
	<optionData id="27081">
		<for>

			<add order="0x60" stat="maxHp" val="128.05"/>
		</for>
	</optionData>
	<optionData id="27082">
		<for>

			<add order="0x60" stat="maxMp" val="57.41"/>
		</for>
	</optionData>
	<optionData id="27083">
		<for>

			<add order="0x60" stat="maxCp" val="252.09"/>
		</for>
	</optionData>
	<optionData id="27084">
		<for>

			<add order="0x60" stat="pAtk" val="63.04"/>
		</for>
	</optionData>
	<optionData id="27085">
		<for>

			<add order="0x60" stat="mAtk" val="81.5"/>
		</for>
	</optionData>
	<optionData id="27086">
		<for>

			<add order="0x60" stat="regHp" val="0.48"/>
		</for>
	</optionData>
	<optionData id="27087">
		<for>

			<add order="0x60" stat="regMp" val="0.2"/>
		</for>
	</optionData>
	<optionData id="27088">
		<for>

			<add order="0x60" stat="regCp" val="0.48"/>
		</for>
	</optionData>
	<optionData id="27089">
		<for>

			<add order="0x60" stat="ratePhysicalEvas" val="2.821"/>
		</for>
	</optionData>
	<optionData id="27090">
		<for>

			<add order="0x60" stat="accPhysical" val="4.113"/>
		</for>
	</optionData>
	<optionData id="27091">
		<for>

			<add order="0x60" stat="pCritRate" val="30.8"/>
		</for>
	</optionData>
	<optionData id="27092">
		<for>

			<add order="0x60" stat="pDef" val="26.07"/>
			<add order="0x60" stat="mDef" val="24.065"/>
		</for>
	</optionData>
	<optionData id="27093">
		<for>

			<add order="0x60" stat="pDef" val="26.07"/>
			<add order="0x60" stat="maxHp" val="64.025"/>
		</for>
	</optionData>
	<optionData id="27094">
		<for>

			<add order="0x60" stat="pDef" val="26.07"/>
			<add order="0x60" stat="maxMp" val="28.705"/>
		</for>
	</optionData>
	<optionData id="27095">
		<for>

			<add order="0x60" stat="pDef" val="26.07"/>
			<add order="0x60" stat="maxCp" val="126.045"/>
		</for>
	</optionData>
	<optionData id="27096">
		<for>

			<add order="0x60" stat="pDef" val="26.07"/>
			<add order="0x60" stat="pAtk" val="31.52"/>
		</for>
	</optionData>
	<optionData id="27097">
		<for>

			<add order="0x60" stat="pDef" val="26.07"/>
			<add order="0x60" stat="mAtk" val="40.75"/>
		</for>
	</optionData>
	<optionData id="27098">
		<for>

			<add order="0x60" stat="pDef" val="26.07"/>
			<add order="0x60" stat="regHp" val="0.24"/>
		</for>
	</optionData>
	<optionData id="27099">
		<for>

			<add order="0x60" stat="pDef" val="26.07"/>
			<add order="0x60" stat="regMp" val="0.1"/>
		</for>
	</optionData>
</list>