<?xml version="1.0" encoding="UTF-8" standalone="no"?><list xmlns:xsi="http://www.w3.org/2001/XMLSchema-instance" xsi:noNamespaceSchemaLocation="../../../../xsd/locationSpawnlist.xsd">
	<spawns name="17_20">
		
		<npc id="20012">
			<spawn heading="42676" respawn="25" x="-74814" y="94702" z="-3731"/>
			<spawn heading="39828" respawn="25" x="-66830" y="98219" z="-3659"/>
			<spawn heading="52675" respawn="25" x="-65624" y="96522" z="-3633"/>
		</npc>
		
		<npc id="20021">
			<spawn heading="34249" respawn="25" x="-68464" y="97561" z="-3679"/>
			<spawn heading="61760" respawn="25" x="-66898" y="97446" z="-3690"/>
			<spawn heading="17128" respawn="25" x="-65668" y="96568" z="-3637"/>
		</npc>
		
		<npc id="20038">
			<spawn heading="39746" respawn="20" x="-74051" y="96605" z="-3698"/>
			<spawn heading="45796" respawn="20" x="-71047" y="96029" z="-3734"/>
		</npc>
		
		<npc id="20078">
			<spawn heading="55586" respawn="26" x="-87093" y="81992" z="-2913"/>
			<spawn heading="0" respawn="26" x="-86964" y="80852" z="-3404"/>
			<spawn heading="0" respawn="26" x="-86359" y="81920" z="-3404"/>
			<spawn heading="0" respawn="26" x="-85789" y="77771" z="-3468"/>
			<spawn heading="0" respawn="26" x="-85755" y="81208" z="-3404"/>
			<spawn heading="18245" respawn="26" x="-85351" y="83447" z="-3286"/>
			<spawn heading="48036" respawn="26" x="-85141" y="78774" z="-3095"/>
			<spawn heading="9008" respawn="26" x="-84994" y="85128" z="-3359"/>
			<spawn heading="19207" respawn="26" x="-84898" y="81463" z="-3194"/>
			<spawn heading="9190" respawn="26" x="-84861" y="88258" z="-3529"/>
			<spawn heading="0" respawn="26" x="-84681" y="77237" z="-3468"/>
			<spawn heading="13340" respawn="26" x="-84593" y="80250" z="-3159"/>
			<spawn heading="2926" respawn="26" x="-83343" y="79454" z="-3265"/>
			<spawn heading="3969" respawn="26" x="-82949" y="78827" z="-3335"/>
			<spawn heading="54324" respawn="26" x="-82312" y="77088" z="-3400"/>
		</npc>
		
		<npc id="20335">
			<spawn heading="30546" respawn="25" x="-72306" y="96723" z="-3714"/>
			<spawn heading="34872" respawn="25" x="-71062" y="98057" z="-3711"/>
			<spawn heading="53946" respawn="25" x="-70254" y="96698" z="-3739"/>
		</npc>
		
		<npc id="20494">
			<spawn heading="61247" x="-95698" y="97852" z="-3536"/>
		</npc>
		
		<npc id="20496">
			<spawn heading="6737" x="-94829" y="97834" z="-3535"/>
		</npc>
		
		<npc id="20499">
			<spawn heading="52973" x="-96196" y="98055" z="-3536"/>
			<spawn heading="48053" x="-95566" y="97015" z="-3537"/>
		</npc>
		
		<npc id="20500">
			<spawn heading="6823" x="-94678" y="98243" z="-3530"/>
		</npc>
		
		<npc id="21023">
			<spawn heading="24493" respawn="26" x="-93819" y="97300" z="-3541"/>
			<spawn heading="32718" respawn="26" x="-93504" y="96117" z="-3547"/>
			<spawn heading="0" respawn="26" x="-93216" y="91901" z="-3664"/>
			<spawn heading="0" respawn="26" x="-92713" y="91367" z="-3664"/>
			<spawn heading="0" respawn="26" x="-92310" y="91011" z="-3664"/>
			<spawn heading="0" respawn="26" x="-92210" y="92257" z="-3664"/>
			<spawn heading="64066" respawn="26" x="-92165" y="97908" z="-3508"/>
			<spawn heading="0" respawn="26" x="-91807" y="91545" z="-3664"/>
			<spawn heading="33135" respawn="26" x="-82086" y="92164" z="-3608"/>
			<spawn heading="0" respawn="26" x="-80847" y="89980" z="-3728"/>
			<spawn heading="51423" respawn="26" x="-80736" y="91181" z="-3704"/>
			<spawn heading="0" respawn="26" x="-80539" y="87221" z="-3544"/>
			<spawn heading="0" respawn="26" x="-80096" y="88181" z="-3497"/>
			<spawn heading="0" respawn="26" x="-79995" y="89071" z="-3497"/>
			<spawn heading="0" respawn="26" x="-79895" y="88181" z="-3497"/>
			<spawn heading="0" respawn="26" x="-79895" y="88537" z="-3497"/>
			<spawn heading="32937" respawn="26" x="-79421" y="92234" z="-3721"/>
			<spawn heading="38703" respawn="26" x="-78139" y="92824" z="-3731"/>
			<spawn heading="0" respawn="26" x="-77433" y="91329" z="-3807"/>
			<spawn heading="26734" respawn="26" x="-76154" y="93392" z="-3711"/>
			<spawn heading="52128" respawn="26" x="-74387" y="93231" z="-3677"/>
			<spawn heading="43772" respawn="26" x="-73557" y="95743" z="-3713"/>
			<spawn heading="55176" respawn="26" x="-72580" y="93981" z="-3683"/>
			<spawn heading="9072" respawn="26" x="-72203" y="98208" z="-3690"/>
			<spawn heading="58328" respawn="26" x="-68695" y="95649" z="-3678"/>
		</npc>
		
		<npc id="21024">
			<spawn heading="41018" respawn="26" x="-95560" y="96005" z="-3529"/>
			<spawn heading="31330" respawn="26" x="-95498" y="98295" z="-3525"/>
			<spawn heading="56123" respawn="26" x="-93627" y="95659" z="-3518"/>
			<spawn heading="17945" respawn="26" x="-92779" y="94785" z="-3481"/>
			<spawn heading="50887" respawn="26" x="-92669" y="96049" z="-3553"/>
			<spawn heading="62933" respawn="26" x="-92568" y="93090" z="-3398"/>
			<spawn heading="46645" respawn="26" x="-91995" y="96200" z="-3565"/>
			<spawn heading="0" respawn="26" x="-91812" y="88055" z="-3649"/>
			<spawn heading="15792" respawn="26" x="-91387" y="94965" z="-3520"/>
			<spawn heading="0" respawn="26" x="-91309" y="87521" z="-3649"/>
			<spawn heading="26684" respawn="26" x="-91245" y="88948" z="-3342"/>
			<spawn heading="0" respawn="26" x="-91007" y="88411" z="-3649"/>
			<spawn heading="53340" respawn="26" x="-90534" y="87621" z="-3431"/>
			<spawn heading="0" respawn="26" x="-89487" y="87115" z="-3649"/>
			<spawn heading="0" respawn="26" x="-89386" y="87649" z="-3649"/>
			<spawn heading="38215" respawn="26" x="-89336" y="92108" z="-2676"/>
			<spawn heading="0" respawn="26" x="-88883" y="86759" z="-3649"/>
			<spawn heading="39634" respawn="26" x="-88832" y="98186" z="-3529"/>
			<spawn heading="0" respawn="26" x="-88783" y="87293" z="-3649"/>
			<spawn heading="0" respawn="26" x="-88781" y="88717" z="-3649"/>
			<spawn heading="11172" respawn="26" x="-88454" y="92853" z="-2507"/>
			<spawn heading="10988" respawn="26" x="-84242" y="87822" z="-3520"/>
			<spawn heading="0" respawn="26" x="-83115" y="86429" z="-3546"/>
			<spawn heading="0" respawn="26" x="-82712" y="86429" z="-3546"/>
			<spawn heading="47398" respawn="26" x="-82623" y="85838" z="-3511"/>
			<spawn heading="16721" respawn="26" x="-82394" y="87151" z="-3547"/>
			<spawn heading="0" respawn="26" x="-82290" y="89012" z="-3691"/>
			<spawn heading="0" respawn="26" x="-82270" y="87969" z="-3561"/>
			<spawn heading="0" respawn="26" x="-82210" y="86607" z="-3546"/>
			<spawn heading="0" respawn="26" x="-80524" y="87925" z="-3534"/>
			<spawn heading="0" respawn="26" x="-80291" y="87825" z="-3533"/>
			<spawn heading="8736" respawn="26" x="-80265" y="90406" z="-3721"/>
			<spawn heading="0" respawn="26" x="-79693" y="88537" z="-3400"/>
			<spawn heading="38161" respawn="26" x="-77008" y="93755" z="-3701"/>
			<spawn heading="30660" respawn="26" x="-76262" y="94972" z="-3692"/>
			<spawn heading="7653" respawn="26" x="-75650" y="94668" z="-3709"/>
			<spawn heading="14460" respawn="26" x="-75065" y="95616" z="-3690"/>
			<spawn heading="0" respawn="26" x="-72554" y="95193" z="-3817"/>
			<spawn heading="0" respawn="26" x="-71447" y="94303" z="-3817"/>
			<spawn heading="5621" respawn="26" x="-71447" y="96911" z="-3718"/>
		</npc>
		
		<npc id="21025">
			<spawn heading="36259" respawn="26" x="-95212" y="95271" z="-3480"/>
			<spawn heading="22732" respawn="26" x="-93923" y="94493" z="-3440"/>
			<spawn heading="35442" respawn="26" x="-93744" y="93572" z="-3386"/>
			<spawn heading="0" respawn="26" x="-92819" y="88055" z="-3649"/>
			<spawn heading="28632" respawn="26" x="-92346" y="89977" z="-3257"/>
			<spawn heading="0" respawn="26" x="-92014" y="88767" z="-3649"/>
			<spawn heading="42585" respawn="26" x="-91498" y="89927" z="-3307"/>
			<spawn heading="58507" respawn="26" x="-91413" y="93954" z="-3414"/>
			<spawn heading="17220" respawn="26" x="-91141" y="92955" z="-3410"/>
			<spawn heading="23621" respawn="26" x="-90872" y="90225" z="-3313"/>
			<spawn heading="51682" respawn="26" x="-90474" y="88956" z="-3377"/>
			<spawn heading="901" respawn="26" x="-90180" y="97773" z="-3512"/>
			<spawn heading="43572" respawn="26" x="-89542" y="91609" z="-2830"/>
			<spawn heading="7559" respawn="26" x="-88524" y="89957" z="-3300"/>
			<spawn heading="35833" respawn="26" x="-88388" y="85882" z="-3300"/>
			<spawn heading="52444" respawn="26" x="-88374" y="88254" z="-3419"/>
			<spawn heading="0" respawn="26" x="-88320" y="84432" z="-3189"/>
			<spawn heading="0" respawn="26" x="-88319" y="83720" z="-3189"/>
			<spawn heading="0" respawn="26" x="-87815" y="83186" z="-3189"/>
			<spawn heading="18185" respawn="26" x="-87772" y="89139" z="-3334"/>
			<spawn heading="0" respawn="26" x="-87412" y="84610" z="-3189"/>
			<spawn heading="18315" respawn="26" x="-86807" y="88378" z="-3392"/>
			<spawn heading="16931" respawn="26" x="-86466" y="90325" z="-3294"/>
			<spawn heading="32000" respawn="26" x="-85857" y="87651" z="-3475"/>
			<spawn heading="0" respawn="26" x="-85757" y="80140" z="-3404"/>
			<spawn heading="12127" respawn="26" x="-84958" y="90200" z="-3346"/>
			<spawn heading="0" respawn="26" x="-84398" y="82213" z="-3278"/>
			<spawn heading="0" respawn="26" x="-84297" y="82391" z="-3278"/>
			<spawn heading="0" respawn="26" x="-84297" y="82747" z="-3278"/>
			<spawn heading="45905" respawn="26" x="-84256" y="84750" z="-3365"/>
			<spawn heading="0" respawn="26" x="-84196" y="81857" z="-3278"/>
			<spawn heading="0" respawn="26" x="-84095" y="82391" z="-3278"/>
			<spawn heading="0" respawn="26" x="-84095" y="82747" z="-3278"/>
			<spawn heading="0" respawn="26" x="-83994" y="82925" z="-3278"/>
			<spawn heading="0" respawn="26" x="-83692" y="82391" z="-3278"/>
			<spawn heading="0" respawn="26" x="-83242" y="86592" z="-3548"/>
			<spawn heading="0" respawn="26" x="-83115" y="87141" z="-3546"/>
			<spawn heading="0" respawn="26" x="-82586" y="82213" z="-3278"/>
			<spawn heading="0" respawn="26" x="-82512" y="86785" z="-3546"/>
			<spawn heading="47015" respawn="26" x="-81842" y="89903" z="-3725"/>
			<spawn heading="24576" respawn="26" x="-81309" y="87802" z="-3549"/>
			<spawn heading="0" respawn="26" x="-81023" y="88715" z="-3533"/>
			<spawn heading="0" respawn="26" x="-80763" y="89249" z="-3533"/>
			<spawn heading="0" respawn="26" x="-80500" y="88893" z="-3533"/>
			<spawn heading="46125" respawn="26" x="-77113" y="92535" z="-3712"/>
		</npc>
		
		<npc id="21026">
			<spawn heading="28124" respawn="26" x="-89876" y="89091" z="-3398"/>
			<spawn heading="52971" respawn="26" x="-87902" y="86984" z="-3420"/>
			<spawn heading="20675" respawn="26" x="-87692" y="88096" z="-3401"/>
			<spawn heading="12923" respawn="26" x="-87425" y="85713" z="-3332"/>
			<spawn heading="23863" respawn="26" x="-87308" y="82295" z="-2909"/>
			<spawn heading="9949" respawn="26" x="-87191" y="91248" z="-3104"/>
			<spawn heading="14605" respawn="26" x="-87149" y="86902" z="-3413"/>
			<spawn heading="0" respawn="26" x="-87111" y="83720" z="-3189"/>
			<spawn heading="0" respawn="26" x="-87110" y="83008" z="-3189"/>
			<spawn heading="52833" respawn="26" x="-86747" y="85293" z="-3309"/>
			<spawn heading="45430" respawn="26" x="-86503" y="82889" z="-3132"/>
			<spawn heading="0" respawn="26" x="-86359" y="80852" z="-3404"/>
			<spawn heading="53805" respawn="26" x="-86187" y="84653" z="-3267"/>
			<spawn heading="0" respawn="26" x="-85956" y="81564" z="-3404"/>
			<spawn heading="36123" respawn="26" x="-85830" y="79214" z="-2978"/>
			<spawn heading="0" respawn="26" x="-85655" y="81386" z="-3404"/>
			<spawn heading="0" respawn="26" x="-85184" y="77415" z="-3468"/>
			<spawn heading="13029" respawn="26" x="-84424" y="79288" z="-3165"/>
			<spawn heading="0" respawn="26" x="-84398" y="82925" z="-3278"/>
			<spawn heading="0" respawn="26" x="-84297" y="83103" z="-3278"/>
			<spawn heading="0" respawn="26" x="-84095" y="82035" z="-3278"/>
			<spawn heading="24246" respawn="26" x="-84059" y="89310" z="-3525"/>
			<spawn heading="0" respawn="26" x="-83894" y="83103" z="-3278"/>
			<spawn heading="33058" respawn="26" x="-83890" y="77849" z="-3292"/>
			<spawn heading="0" respawn="26" x="-83794" y="81857" z="-3278"/>
			<spawn heading="0" respawn="26" x="-83793" y="82213" z="-3278"/>
			<spawn heading="0" respawn="26" x="-83692" y="82747" z="-3278"/>
			<spawn heading="0" respawn="26" x="-83490" y="82035" z="-3278"/>
			<spawn heading="0" respawn="26" x="-83390" y="82213" z="-3278"/>
			<spawn heading="27340" respawn="26" x="-82933" y="88005" z="-3565"/>
			<spawn heading="56129" respawn="26" x="-80743" y="86612" z="-3546"/>
		</npc>
		
		<npc id="27165">
			<spawn heading="0" respawn="180" x="-81247" y="75607" z="-3360"/>
		</npc>
		
		<npc id="31031">
			<spawn heading="16384" respawn="5" x="-79884" y="86529" z="-5182"/>
			<spawn heading="16384" respawn="5" x="-76973" y="87136" z="-5182"/>
		</npc>
		
		<npc id="31137">
			<spawn heading="49000" x="-80208" y="87120" z="-5153"/>
		</npc>
		
		<npc id="31138">
			<spawn heading="49000" x="-77200" y="87728" z="-5153"/>
		</npc>
		
		<npc id="31139">
			<spawn heading="32500" x="-76096" y="87136" z="-5153"/>
		</npc>
		
		<npc id="31140">
			<spawn heading="16500" x="-76944" y="86544" z="-5153"/>
		</npc>
		
		<npc id="31141">
			<spawn heading="16500" x="-79968" y="85936" z="-5153"/>
		</npc>
	</spawns>
</list>