<?xml version="1.0" encoding="UTF-8" standalone="no"?><list xmlns:xsi="http://www.w3.org/2001/XMLSchema-instance" xsi:noNamespaceSchemaLocation="../../../../xsd/locationSpawnlist.xsd">
	<spawns name="21_21">
		
		<npc id="18266">
			<spawn heading="0" respawn="0" x="41398" y="119122" z="-2184"/>
			<spawn heading="0" respawn="0" x="49816" y="112112" z="-1976"/>
		</npc>
		
		<npc id="20063">
			<spawn heading="26188" x="35778" y="113902" z="-1560"/>
			<spawn heading="39689" x="36235" y="113583" z="-1624"/>
			<spawn heading="35845" x="36244" y="113554" z="-1632"/>
			<spawn heading="0" x="36557" y="118971" z="-1792"/>
			<spawn heading="25067" x="36757" y="115515" z="-1152"/>
			<spawn heading="25156" x="37015" y="123583" z="-1976"/>
			<spawn heading="31634" x="37151" y="115556" z="-1256"/>
			<spawn heading="26004" x="37481" y="119987" z="-1544"/>
			<spawn heading="64522" x="37594" y="120023" z="-1560"/>
			<spawn heading="42252" x="38580" y="124703" z="-1904"/>
			<spawn heading="58957" x="40197" y="124822" z="-1944"/>
			<spawn heading="49863" x="40848" y="125927" z="-1800"/>
			<spawn heading="46964" x="41385" y="118988" z="-2184"/>
			<spawn heading="15429" x="41507" y="127030" z="-2032"/>
			<spawn heading="46334" x="41956" y="120879" z="-1728"/>
			<spawn heading="32641" x="42733" y="121756" z="-1712"/>
			<spawn heading="2370" x="42790" y="121143" z="-1696"/>
			<spawn heading="6370" x="48709" y="125888" z="-3632"/>
			<spawn heading="62211" x="49152" y="124915" z="-3496"/>
			<spawn heading="0" x="50653" y="127553" z="-3688"/>
			<spawn heading="59957" x="51649" y="125821" z="-3568"/>
			<spawn heading="27649" x="51991" y="123961" z="-3216"/>
			<spawn heading="19539" x="52591" y="120912" z="-3208"/>
			<spawn heading="18145" x="52616" y="121037" z="-3224"/>
			<spawn heading="52769" x="52791" y="127237" z="-3448"/>
			<spawn heading="28058" x="53052" y="123585" z="-3280"/>
			<spawn heading="12485" x="53571" y="127113" z="-3240"/>
			<spawn heading="0" x="53670" y="121760" z="-3152"/>
			<spawn heading="10496" x="55399" y="120923" z="-3184"/>
			<spawn heading="21580" x="55486" y="124120" z="-3296"/>
			<spawn heading="40693" x="56002" y="116266" z="-2072"/>
			<spawn heading="39453" x="56138" y="119283" z="-2456"/>
			<spawn heading="9838" x="56710" y="119808" z="-2560"/>
			<spawn heading="10180" x="57345" y="117340" z="-2664"/>
			<spawn heading="7380" x="57380" y="117321" z="-2680"/>
		</npc>
		
		<npc id="20205">
			<spawn heading="61042" respawn="24" x="36714" y="130826" z="-3201"/>
		</npc>
		
		<npc id="20207">
			<spawn heading="58957" x="34929" y="113064" z="-1912"/>
			<spawn heading="29890" x="34993" y="112599" z="-2000"/>
			<spawn heading="46769" x="35122" y="112617" z="-2000"/>
			<spawn heading="24340" x="35397" y="112669" z="-1976"/>
			<spawn heading="40160" x="35643" y="110692" z="-1568"/>
			<spawn heading="3033" x="35688" y="116330" z="-1408"/>
			<spawn heading="60169" x="35810" y="117750" z="-1584"/>
			<spawn heading="7246" x="35863" y="116797" z="-1472"/>
			<spawn heading="55523" x="36244" y="116193" z="-1264"/>
			<spawn heading="27358" x="36404" y="114876" z="-1168"/>
			<spawn heading="22331" x="36432" y="115901" z="-1168"/>
			<spawn heading="28947" x="36507" y="117438" z="-1752"/>
			<spawn heading="24340" x="36551" y="116867" z="-1584"/>
			<spawn heading="4323" x="36625" y="114435" z="-1344"/>
			<spawn heading="45797" x="36748" y="114812" z="-1216"/>
			<spawn heading="19739" x="36911" y="115661" z="-1184"/>
			<spawn heading="34089" x="37378" y="109227" z="-1456"/>
			<spawn heading="48014" x="37418" y="106973" z="-1312"/>
			<spawn heading="19460" x="37494" y="116832" z="-1632"/>
			<spawn heading="9529" x="37558" y="123509" z="-2112"/>
			<spawn heading="57568" x="37701" y="108901" z="-1480"/>
			<spawn heading="56369" x="37745" y="125604" z="-1872"/>
			<spawn heading="20581" x="37796" y="107627" z="-1368"/>
			<spawn heading="35827" x="37855" y="122464" z="-2056"/>
			<spawn heading="59233" x="37882" y="108425" z="-1472"/>
			<spawn heading="57926" x="37891" y="121936" z="-1896"/>
			<spawn heading="22129" x="38665" y="121589" z="-1944"/>
			<spawn heading="16192" x="39018" y="127058" z="-1920"/>
			<spawn heading="58758" x="39366" y="123815" z="-2112"/>
			<spawn heading="20070" x="39368" y="120503" z="-1928"/>
			<spawn heading="15621" x="39537" y="117191" z="-1736"/>
			<spawn heading="45219" x="39980" y="117348" z="-1656"/>
			<spawn heading="47254" x="40279" y="117520" z="-1688"/>
			<spawn heading="26951" x="40489" y="125447" z="-1776"/>
			<spawn heading="65441" x="40658" y="117156" z="-1560"/>
			<spawn heading="14013" x="40981" y="125324" z="-1984"/>
			<spawn heading="61727" x="41085" y="116262" z="-1800"/>
			<spawn heading="39282" x="41207" y="125760" z="-1952"/>
			<spawn heading="53862" x="41402" y="119261" z="-2184"/>
			<spawn heading="42207" x="41458" y="116930" z="-1768"/>
			<spawn heading="53016" x="41521" y="120377" z="-1840"/>
			<spawn heading="45499" x="41689" y="125905" z="-2072"/>
			<spawn heading="41362" x="41817" y="120658" z="-1768"/>
			<spawn heading="0" x="41846" y="118870" z="-2096"/>
			<spawn heading="33715" x="41871" y="126801" z="-2096"/>
			<spawn heading="45886" x="41885" y="127100" z="-2160"/>
			<spawn heading="12786" x="41938" y="118816" z="-2160"/>
			<spawn heading="37042" x="42020" y="117506" z="-1824"/>
			<spawn heading="8820" x="42180" y="118205" z="-1832"/>
			<spawn heading="13481" x="42296" y="122460" z="-2008"/>
			<spawn heading="20823" x="42584" y="117618" z="-1912"/>
			<spawn heading="21749" x="42654" y="120690" z="-1672"/>
			<spawn heading="22540" x="42663" y="120595" z="-1664"/>
			<spawn heading="41161" x="42775" y="117337" z="-1936"/>
			<spawn heading="42497" x="42889" y="119332" z="-1656"/>
			<spawn heading="46185" x="42908" y="119471" z="-1640"/>
			<spawn heading="54073" x="43517" y="122528" z="-2336"/>
			<spawn heading="22199" x="44034" y="119301" z="-1880"/>
			<spawn heading="16861" x="45254" y="118845" z="-2224"/>
			<spawn heading="30411" x="49982" y="120733" z="-2704"/>
			<spawn heading="48521" x="49990" y="114877" z="-1440"/>
			<spawn heading="6159" x="50245" y="115337" z="-1488"/>
			<spawn heading="48711" x="50322" y="115305" z="-1440"/>
			<spawn heading="3033" x="50332" y="115022" z="-1344"/>
			<spawn heading="64204" x="50942" y="120610" z="-2792"/>
			<spawn heading="8124" x="50955" y="120679" z="-2768"/>
			<spawn heading="4235" x="51019" y="112855" z="-1472"/>
			<spawn heading="47699" x="51309" y="113365" z="-1392"/>
			<spawn heading="50286" x="51735" y="121345" z="-2760"/>
			<spawn heading="50286" x="52026" y="122961" z="-2968"/>
			<spawn heading="64326" x="52130" y="123858" z="-3216"/>
			<spawn heading="14755" x="52865" y="123161" z="-3160"/>
			<spawn heading="17052" x="52890" y="121762" z="-3152"/>
			<spawn heading="21092" x="52937" y="123561" z="-3248"/>
			<spawn heading="0" x="53106" y="115830" z="-1632"/>
			<spawn heading="0" x="53670" y="121493" z="-3176"/>
			<spawn heading="59614" x="53727" y="110954" z="-1208"/>
			<spawn heading="0" x="53782" y="116942" z="-1408"/>
			<spawn heading="5155" x="54176" y="115543" z="-1768"/>
			<spawn heading="23567" x="54313" y="115463" z="-1808"/>
			<spawn heading="38615" x="54443" y="115988" z="-1720"/>
			<spawn heading="19368" x="54753" y="112292" z="-1464"/>
			<spawn heading="8415" x="54831" y="115564" z="-1912"/>
			<spawn heading="10356" x="55291" y="119457" z="-2544"/>
			<spawn heading="10921" x="55436" y="120917" z="-3160"/>
			<spawn heading="9748" x="55469" y="120921" z="-3136"/>
			<spawn heading="8057" x="55487" y="120929" z="-3136"/>
			<spawn heading="10356" x="55489" y="120893" z="-3104"/>
			<spawn heading="12036" x="55712" y="120900" z="-3024"/>
			<spawn heading="64137" x="56158" y="119745" z="-2600"/>
			<spawn heading="0" x="56177" y="112392" z="-1480"/>
			<spawn heading="0" x="56288" y="111006" z="-1424"/>
			<spawn heading="3986" x="57085" y="112087" z="-1712"/>
			<spawn heading="49090" x="57350" y="112956" z="-1736"/>
			<spawn heading="0" x="57352" y="111175" z="-1664"/>
			<spawn heading="59791" x="57357" y="117433" z="-2648"/>
			<spawn heading="42291" x="57365" y="117335" z="-2672"/>
			<spawn heading="2508" x="57455" y="117460" z="-2680"/>
			<spawn heading="48963" x="57480" y="117618" z="-2664"/>
			<spawn heading="508" x="57500" y="117545" z="-2680"/>
			<spawn heading="44120" x="57568" y="117619" z="-2688"/>
			<spawn heading="7484" x="57609" y="117648" z="-2696"/>
		</npc>
		
		<npc id="20208">
			<spawn heading="55260" x="35096" y="112227" z="-1928"/>
			<spawn heading="60106" x="35208" y="113197" z="-1872"/>
			<spawn heading="17574" x="35450" y="111703" z="-1856"/>
			<spawn heading="12967" x="35627" y="115314" z="-1256"/>
			<spawn heading="21221" x="35942" y="116233" z="-1336"/>
			<spawn heading="40426" x="36239" y="110563" z="-1408"/>
			<spawn heading="13951" x="36328" y="110800" z="-1456"/>
			<spawn heading="28016" x="36526" y="116114" z="-1232"/>
			<spawn heading="52211" x="36537" y="116224" z="-1264"/>
			<spawn heading="39935" x="37139" y="108222" z="-1280"/>
			<spawn heading="12335" x="37395" y="108657" z="-1392"/>
			<spawn heading="13690" x="37703" y="109029" z="-1488"/>
			<spawn heading="30967" x="37741" y="107290" z="-1328"/>
			<spawn heading="2785" x="38121" y="107033" z="-1320"/>
			<spawn heading="30876" x="39288" y="116887" z="-1816"/>
			<spawn heading="41562" x="39346" y="116567" z="-1800"/>
			<spawn heading="14614" x="39447" y="114158" z="-2072"/>
			<spawn heading="38902" x="39457" y="113758" z="-2072"/>
			<spawn heading="31963" x="39667" y="113527" z="-2072"/>
			<spawn heading="14175" x="39690" y="116778" z="-1704"/>
			<spawn heading="54497" x="39752" y="114118" z="-2072"/>
			<spawn heading="52629" x="39877" y="104845" z="-1936"/>
			<spawn heading="20739" x="40189" y="113939" z="-2072"/>
			<spawn heading="61380" x="40360" y="115501" z="-1864"/>
			<spawn heading="49469" x="40587" y="116889" z="-1544"/>
			<spawn heading="20823" x="40776" y="104627" z="-1984"/>
			<spawn heading="3204" x="40807" y="104779" z="-1984"/>
			<spawn heading="8326" x="40909" y="104518" z="-2008"/>
			<spawn heading="29591" x="41052" y="117793" z="-1696"/>
			<spawn heading="47824" x="41498" y="119842" z="-1896"/>
			<spawn heading="29741" x="41804" y="121575" z="-1824"/>
			<spawn heading="36984" x="42076" y="121127" z="-1688"/>
			<spawn heading="27990" x="42344" y="117491" z="-1880"/>
			<spawn heading="34481" x="42385" y="117416" z="-1904"/>
			<spawn heading="62151" x="42404" y="117099" z="-1912"/>
			<spawn heading="21561" x="42509" y="118822" z="-1688"/>
			<spawn heading="7652" x="42607" y="121830" z="-1696"/>
			<spawn heading="41362" x="42720" y="122374" z="-1984"/>
			<spawn heading="3957" x="42748" y="119040" z="-1672"/>
			<spawn heading="51051" x="42982" y="118681" z="-1704"/>
			<spawn heading="21006" x="43047" y="119537" z="-1640"/>
			<spawn heading="56541" x="44170" y="119587" z="-1944"/>
			<spawn heading="0" x="45519" y="116290" z="-2048"/>
			<spawn heading="0" x="45883" y="116494" z="-2176"/>
			<spawn heading="0" x="46065" y="115746" z="-1848"/>
			<spawn heading="0" x="46429" y="116426" z="-2160"/>
			<spawn heading="24901" x="46775" y="116228" z="-2192"/>
			<spawn heading="44035" x="49343" y="114315" z="-1576"/>
			<spawn heading="27293" x="49667" y="113582" z="-1440"/>
			<spawn heading="17002" x="49705" y="114360" z="-1320"/>
			<spawn heading="48584" x="49867" y="114897" z="-1512"/>
			<spawn heading="54638" x="50039" y="114195" z="-1192"/>
			<spawn heading="58290" x="50191" y="114949" z="-1384"/>
			<spawn heading="7788" x="50357" y="115362" z="-1432"/>
			<spawn heading="47826" x="50394" y="115109" z="-1344"/>
			<spawn heading="43046" x="50399" y="115248" z="-1384"/>
			<spawn heading="0" x="52261" y="115274" z="-1544"/>
			<spawn heading="19469" x="52461" y="113253" z="-2000"/>
			<spawn heading="15240" x="52628" y="114150" z="-2024"/>
			<spawn heading="14715" x="52802" y="115980" z="-1672"/>
			<spawn heading="49784" x="52860" y="111085" z="-1656"/>
			<spawn heading="7650" x="53008" y="114290" z="-2024"/>
			<spawn heading="0" x="53148" y="114204" z="-1992"/>
			<spawn heading="22516" x="53192" y="116518" z="-1472"/>
			<spawn heading="36720" x="53384" y="110951" z="-1336"/>
			<spawn heading="50950" x="53481" y="109637" z="-1440"/>
			<spawn heading="19151" x="53914" y="115335" z="-1752"/>
			<spawn heading="2983" x="53974" y="116408" z="-1456"/>
			<spawn heading="0" x="54213" y="109637" z="-1120"/>
			<spawn heading="50953" x="54386" y="116785" z="-1480"/>
			<spawn heading="14175" x="54394" y="115932" z="-1736"/>
			<spawn heading="0" x="54457" y="109010" z="-1104"/>
			<spawn heading="35014" x="54551" y="109849" z="-1048"/>
			<spawn heading="43726" x="54818" y="112485" z="-1528"/>
			<spawn heading="43257" x="55478" y="108671" z="-1016"/>
			<spawn heading="13148" x="55581" y="112586" z="-1544"/>
			<spawn heading="17527" x="55873" y="116382" z="-1968"/>
			<spawn heading="0" x="55921" y="109637" z="-1072"/>
			<spawn heading="48219" x="55934" y="109402" z="-1080"/>
			<spawn heading="51675" x="56509" y="111522" z="-1616"/>
			<spawn heading="0" x="56554" y="111851" z="-1648"/>
			<spawn heading="0" x="56554" y="112358" z="-1560"/>
			<spawn heading="13178" x="56673" y="112530" z="-1568"/>
			<spawn heading="58151" x="57011" y="112058" z="-1712"/>
			<spawn heading="8641" x="57356" y="117440" z="-2648"/>
			<spawn heading="142" x="57411" y="117665" z="-2632"/>
			<spawn heading="64200" x="57450" y="113124" z="-1752"/>
			<spawn heading="45061" x="57618" y="112020" z="-1808"/>
			<spawn heading="15808" x="58870" y="111533" z="-1792"/>
			<spawn heading="0" x="59095" y="110843" z="-1568"/>
			<spawn heading="0" x="59245" y="110958" z="-1688"/>
		</npc>
		
		<npc id="20209">
			<spawn heading="48821" x="38153" y="111278" z="-1472"/>
			<spawn heading="48868" x="39762" y="116744" z="-1688"/>
			<spawn heading="41584" x="39788" y="113805" z="-2072"/>
			<spawn heading="33337" x="39945" y="107540" z="-1552"/>
			<spawn heading="31247" x="40198" y="104905" z="-1976"/>
			<spawn heading="64137" x="40228" y="114183" z="-2072"/>
			<spawn heading="12273" x="40530" y="116689" z="-1592"/>
			<spawn heading="32895" x="40652" y="105328" z="-1816"/>
			<spawn heading="64871" x="40993" y="117427" z="-1624"/>
			<spawn heading="19077" x="41337" y="106600" z="-1520"/>
			<spawn heading="4984" x="41759" y="113729" z="-1512"/>
			<spawn heading="25715" x="41765" y="111200" z="-856"/>
			<spawn heading="29951" x="42190" y="114431" z="-1744"/>
			<spawn heading="61980" x="42198" y="112675" z="-1192"/>
			<spawn heading="5375" x="42843" y="107228" z="-1160"/>
			<spawn heading="54626" x="42923" y="118507" z="-1744"/>
			<spawn heading="19423" x="42996" y="111720" z="-1360"/>
			<spawn heading="9814" x="43079" y="105958" z="-1648"/>
			<spawn heading="27001" x="43328" y="110615" z="-1176"/>
			<spawn heading="18098" x="44618" y="118838" z="-2024"/>
			<spawn heading="0" x="45701" y="115950" z="-1880"/>
			<spawn heading="62556" x="45887" y="115962" z="-1920"/>
			<spawn heading="4623" x="49911" y="112277" z="-1976"/>
			<spawn heading="0" x="50691" y="105071" z="-1352"/>
			<spawn heading="0" x="50691" y="105587" z="-1496"/>
			<spawn heading="3491" x="51701" y="105487" z="-1488"/>
			<spawn heading="46587" x="52176" y="105610" z="-1496"/>
			<spawn heading="0" x="52235" y="104039" z="-800"/>
			<spawn heading="6297" x="52507" y="103960" z="-864"/>
			<spawn heading="41027" x="52911" y="104275" z="-856"/>
			<spawn heading="31055" x="54515" y="112505" z="-1552"/>
			<spawn heading="47192" x="54848" y="105807" z="-1152"/>
			<spawn heading="56405" x="54909" y="107795" z="-1040"/>
			<spawn heading="31534" x="55057" y="108724" z="-1032"/>
			<spawn heading="34183" x="55205" y="107031" z="-1176"/>
			<spawn heading="62542" x="55378" y="110311" z="-1048"/>
			<spawn heading="63580" x="55394" y="111632" z="-1264"/>
			<spawn heading="64677" x="55408" y="113723" z="-2056"/>
			<spawn heading="0" x="56288" y="110668" z="-1400"/>
			<spawn heading="0" x="57352" y="112358" z="-1736"/>
		</npc>
		
		<npc id="20210">
			<spawn heading="41762" x="39775" y="109963" z="-1104"/>
			<spawn heading="40507" x="39872" y="107108" z="-1648"/>
			<spawn heading="63235" x="40003" y="112222" z="-1152"/>
			<spawn heading="17243" x="40133" y="111051" z="-1008"/>
			<spawn heading="47168" x="40523" y="113603" z="-2072"/>
			<spawn heading="56810" x="40524" y="111410" z="-848"/>
			<spawn heading="58686" x="40536" y="111119" z="-888"/>
			<spawn heading="10158" x="40912" y="108047" z="-1040"/>
			<spawn heading="46689" x="41027" y="106537" z="-1600"/>
			<spawn heading="25110" x="41061" y="107809" z="-1056"/>
			<spawn heading="1190" x="41129" y="111248" z="-808"/>
			<spawn heading="62837" x="41213" y="106746" z="-1480"/>
			<spawn heading="62260" x="41640" y="107794" z="-768"/>
			<spawn heading="59229" x="41654" y="112570" z="-1128"/>
			<spawn heading="52629" x="41848" y="111825" z="-1008"/>
			<spawn heading="64346" x="42054" y="108598" z="-520"/>
			<spawn heading="36563" x="42316" y="113640" z="-1432"/>
			<spawn heading="56842" x="42348" y="111060" z="-872"/>
			<spawn heading="31770" x="42552" y="106134" z="-1648"/>
			<spawn heading="60531" x="42611" y="114480" z="-1760"/>
			<spawn heading="22042" x="42744" y="111014" z="-936"/>
			<spawn heading="56205" x="42789" y="105205" z="-1648"/>
			<spawn heading="31447" x="42823" y="114761" z="-1808"/>
			<spawn heading="34183" x="42899" y="114008" z="-1552"/>
			<spawn heading="60192" x="43390" y="102689" z="-1424"/>
			<spawn heading="37520" x="43644" y="114425" z="-1592"/>
			<spawn heading="47192" x="44041" y="102652" z="-1472"/>
			<spawn heading="37563" x="44231" y="111977" z="-1904"/>
			<spawn heading="55732" x="44283" y="102942" z="-1512"/>
			<spawn heading="65058" x="44349" y="112185" z="-1912"/>
			<spawn heading="61338" x="44402" y="112019" z="-1904"/>
			<spawn heading="22280" x="44613" y="102857" z="-1504"/>
			<spawn heading="46095" x="44627" y="106506" z="-1080"/>
			<spawn heading="56181" x="44685" y="106521" z="-1056"/>
			<spawn heading="29591" x="44817" y="104634" z="-1464"/>
			<spawn heading="23836" x="45151" y="106710" z="-872"/>
			<spawn heading="45956" x="45710" y="105134" z="-1136"/>
			<spawn heading="61239" x="46750" y="106297" z="-872"/>
			<spawn heading="523" x="47105" y="105451" z="-1136"/>
			<spawn heading="0" x="47377" y="104698" z="-1488"/>
			<spawn heading="57815" x="47379" y="108686" z="-2008"/>
			<spawn heading="0" x="47711" y="108957" z="-1880"/>
			<spawn heading="23630" x="47981" y="107487" z="-1416"/>
			<spawn heading="43492" x="48463" y="107364" z="-1328"/>
			<spawn heading="0" x="49147" y="104297" z="-1472"/>
			<spawn heading="35206" x="49279" y="111924" z="-2024"/>
			<spawn heading="53086" x="49365" y="108047" z="-1096"/>
			<spawn heading="0" x="49480" y="112632" z="-1912"/>
			<spawn heading="59281" x="49678" y="106890" z="-1192"/>
			<spawn heading="48711" x="49772" y="112194" z="-1976"/>
			<spawn heading="0" x="49919" y="103523" z="-1120"/>
			<spawn heading="40360" x="50135" y="106421" z="-1400"/>
			<spawn heading="5261" x="50250" y="108281" z="-1064"/>
			<spawn heading="0" x="50425" y="106461" z="-1432"/>
			<spawn heading="47926" x="50890" y="108513" z="-1368"/>
			<spawn heading="44570" x="50937" y="109237" z="-1408"/>
			<spawn heading="6296" x="51349" y="106024" z="-1560"/>
			<spawn heading="0" x="51463" y="106103" z="-1560"/>
			<spawn heading="28975" x="51633" y="106034" z="-1560"/>
			<spawn heading="0" x="51849" y="105071" z="-1240"/>
			<spawn heading="42567" x="52113" y="104035" z="-784"/>
			<spawn heading="61974" x="52147" y="104068" z="-784"/>
			<spawn heading="14151" x="52934" y="106350" z="-1584"/>
			<spawn heading="0" x="53007" y="105071" z="-1072"/>
			<spawn heading="13402" x="53160" y="105790" z="-1520"/>
			<spawn heading="7473" x="53189" y="113800" z="-2064"/>
			<spawn heading="0" x="53725" y="108383" z="-1472"/>
			<spawn heading="34484" x="54190" y="109931" z="-1104"/>
			<spawn heading="53040" x="54403" y="109137" z="-1144"/>
			<spawn heading="49848" x="54493" y="109363" z="-1064"/>
			<spawn heading="0" x="54648" y="109226" z="-1024"/>
			<spawn heading="45114" x="54768" y="108684" z="-1072"/>
			<spawn heading="8393" x="54800" y="109318" z="-984"/>
			<spawn heading="61939" x="54968" y="109792" z="-1000"/>
			<spawn heading="13343" x="55038" y="110673" z="-1056"/>
			<spawn heading="9811" x="55194" y="107272" z="-1096"/>
			<spawn heading="50166" x="55310" y="106194" z="-1232"/>
			<spawn heading="0" x="55656" y="109976" z="-1000"/>
			<spawn heading="44232" x="55742" y="107205" z="-1280"/>
			<spawn heading="32199" x="55874" y="108772" z="-1080"/>
			<spawn heading="0" x="56379" y="105302" z="-1488"/>
			<spawn heading="0" x="56409" y="108174" z="-1384"/>
			<spawn heading="41429" x="56562" y="105246" z="-1488"/>
			<spawn heading="46140" x="56679" y="109237" z="-1400"/>
			<spawn heading="29030" x="57315" y="105702" z="-1488"/>
			<spawn heading="0" x="57385" y="110055" z="-1472"/>
			<spawn heading="0" x="58870" y="110843" z="-1664"/>
			<spawn heading="0" x="59095" y="110613" z="-1568"/>
		</npc>
		
		<npc id="20211">
			<spawn heading="34630" x="38127" y="112086" z="-1576"/>
			<spawn heading="25424" x="39699" y="111388" z="-1024"/>
			<spawn heading="52673" x="40006" y="107859" z="-1448"/>
			<spawn heading="55998" x="40011" y="110119" z="-960"/>
			<spawn heading="40531" x="40017" y="107225" z="-1616"/>
			<spawn heading="44317" x="41108" y="111635" z="-848"/>
			<spawn heading="31676" x="41144" y="106647" z="-1520"/>
			<spawn heading="0" x="41269" y="113576" z="-1552"/>
			<spawn heading="34089" x="41316" y="108788" z="-496"/>
			<spawn heading="59067" x="41929" y="106568" z="-1488"/>
			<spawn heading="1154" x="41961" y="110497" z="-720"/>
			<spawn heading="57210" x="42001" y="114067" z="-1600"/>
			<spawn heading="31581" x="42109" y="105638" z="-1648"/>
			<spawn heading="4580" x="42224" y="108682" z="-480"/>
			<spawn heading="7805" x="42839" y="114382" z="-1688"/>
			<spawn heading="6079" x="43034" y="102950" z="-1400"/>
			<spawn heading="45588" x="43083" y="110830" z="-1040"/>
			<spawn heading="59166" x="43379" y="102663" z="-1424"/>
			<spawn heading="52688" x="43870" y="106076" z="-1272"/>
			<spawn heading="31821" x="44011" y="112327" z="-1912"/>
			<spawn heading="60510" x="44030" y="103208" z="-1512"/>
			<spawn heading="6159" x="44844" y="112553" z="-1912"/>
			<spawn heading="7990" x="46600" y="106639" z="-816"/>
			<spawn heading="39689" x="46703" y="104724" z="-1392"/>
			<spawn heading="15145" x="47122" y="105611" z="-1144"/>
			<spawn heading="8393" x="47138" y="106214" z="-976"/>
			<spawn heading="48846" x="47232" y="108494" z="-2008"/>
			<spawn heading="18405" x="47272" y="107091" z="-1160"/>
			<spawn heading="46529" x="48430" y="106389" z="-1264"/>
			<spawn heading="0" x="48855" y="105961" z="-1512"/>
			<spawn heading="49058" x="49114" y="111901" z="-2032"/>
			<spawn heading="28833" x="49889" y="108012" z="-1040"/>
			<spawn heading="50293" x="50259" y="108082" z="-1096"/>
			<spawn heading="25515" x="50448" y="108234" z="-1160"/>
			<spawn heading="30281" x="50643" y="109625" z="-1400"/>
			<spawn heading="13709" x="51007" y="108032" z="-1472"/>
			<spawn heading="24911" x="56941" y="105782" z="-1488"/>
			<spawn heading="15382" x="57035" y="105936" z="-1488"/>
			<spawn heading="34997" x="59020" y="111763" z="-1768"/>
		</npc>
		
		<npc id="20266">
			<spawn heading="33276" respawn="24" x="33419" y="131007" z="-3294"/>
			<spawn heading="34344" respawn="24" x="34538" y="130753" z="-3294"/>
		</npc>
		
		<npc id="20547">
			<spawn heading="9899" x="35873" y="120168" z="-1320"/>
			<spawn heading="38028" x="36787" y="124114" z="-1944"/>
			<spawn heading="11334" x="37641" y="124460" z="-1960"/>
			<spawn heading="15173" x="37745" y="125334" z="-1896"/>
			<spawn heading="0" x="37966" y="123617" z="-2272"/>
			<spawn heading="18582" x="38448" y="120963" z="-1688"/>
			<spawn heading="13989" x="38552" y="120422" z="-1672"/>
			<spawn heading="40827" x="38676" y="126782" z="-1888"/>
			<spawn heading="17845" x="38842" y="120732" z="-1784"/>
			<spawn heading="30151" x="39153" y="121024" z="-1944"/>
			<spawn heading="16383" x="39190" y="120114" z="-1848"/>
			<spawn heading="46425" x="39467" y="124405" z="-1992"/>
			<spawn heading="29501" x="39605" y="120386" z="-1984"/>
			<spawn heading="24441" x="39679" y="126421" z="-1616"/>
			<spawn heading="38049" x="39699" y="124677" z="-1936"/>
			<spawn heading="3686" x="39763" y="124459" z="-2040"/>
			<spawn heading="28544" x="40342" y="126396" z="-1672"/>
			<spawn heading="30800" x="40624" y="127141" z="-1808"/>
			<spawn heading="12002" x="40839" y="125473" z="-1864"/>
			<spawn heading="56909" x="41028" y="126029" z="-1848"/>
			<spawn heading="59034" x="41356" y="127191" z="-2016"/>
			<spawn heading="64137" x="41884" y="126762" z="-2096"/>
			<spawn heading="40627" x="49466" y="124766" z="-3432"/>
			<spawn heading="21955" x="49554" y="125813" z="-3552"/>
			<spawn heading="41898" x="49723" y="124855" z="-3392"/>
			<spawn heading="56448" x="49979" y="124809" z="-3352"/>
			<spawn heading="32577" x="49997" y="121783" z="-2464"/>
			<spawn heading="36633" x="50136" y="119776" z="-3176"/>
			<spawn heading="10638" x="50223" y="125528" z="-3528"/>
			<spawn heading="6558" x="50309" y="119729" z="-3232"/>
			<spawn heading="62406" x="50922" y="124759" z="-3328"/>
			<spawn heading="2647" x="50922" y="127780" z="-3712"/>
			<spawn heading="7650" x="51038" y="127501" z="-3712"/>
			<spawn heading="37098" x="51045" y="121183" z="-2568"/>
			<spawn heading="15717" x="51060" y="120964" z="-2656"/>
			<spawn heading="42164" x="51151" y="119857" z="-3320"/>
			<spawn heading="8191" x="51171" y="120977" z="-2696"/>
			<spawn heading="27634" x="51181" y="119755" z="-3360"/>
			<spawn heading="63564" x="51318" y="125221" z="-3488"/>
			<spawn heading="5644" x="51498" y="125570" z="-3552"/>
			<spawn heading="10268" x="51537" y="120946" z="-2864"/>
			<spawn heading="808" x="51586" y="127215" z="-3712"/>
			<spawn heading="55998" x="51744" y="127282" z="-3712"/>
			<spawn heading="65058" x="51913" y="124393" z="-3296"/>
			<spawn heading="33337" x="52027" y="123900" z="-3208"/>
			<spawn heading="35233" x="52339" y="127726" z="-3400"/>
			<spawn heading="63564" x="52365" y="121013" z="-3128"/>
			<spawn heading="55391" x="52636" y="123594" z="-3208"/>
			<spawn heading="26298" x="52693" y="121038" z="-3240"/>
			<spawn heading="64137" x="52878" y="128671" z="-3064"/>
			<spawn heading="9033" x="53034" y="120964" z="-3288"/>
			<spawn heading="34988" x="53125" y="122054" z="-3128"/>
			<spawn heading="38196" x="53404" y="121686" z="-3200"/>
			<spawn heading="44296" x="53414" y="121112" z="-3256"/>
			<spawn heading="39077" x="53659" y="120913" z="-3312"/>
			<spawn heading="30040" x="53688" y="121413" z="-3232"/>
			<spawn heading="713" x="53706" y="122937" z="-3272"/>
			<spawn heading="14614" x="53736" y="127297" z="-3176"/>
			<spawn heading="41027" x="54077" y="121750" z="-3296"/>
			<spawn heading="0" x="54338" y="128001" z="-3008"/>
			<spawn heading="57546" x="55022" y="123423" z="-3504"/>
			<spawn heading="8683" x="55338" y="123650" z="-3464"/>
			<spawn heading="14921" x="55355" y="123674" z="-3456"/>
			<spawn heading="34347" x="55491" y="124180" z="-3272"/>
		</npc>
		
		<npc id="20549">
			<spawn heading="52569" x="39975" y="111622" z="-944"/>
			<spawn heading="1524" x="41008" y="111862" z="-856"/>
			<spawn heading="65155" x="41642" y="108469" z="-616"/>
			<spawn heading="41558" x="43194" y="110512" z="-1120"/>
			<spawn heading="24158" x="45907" y="105930" z="-864"/>
			<spawn heading="2954" x="46790" y="106507" z="-864"/>
			<spawn heading="54583" x="50211" y="108013" z="-1096"/>
		</npc>
		
		<npc id="20551">
			<spawn heading="39371" respawn="22" x="65390" y="109624" z="-3665"/>
			<spawn heading="42368" respawn="22" x="65406" y="115883" z="-3656"/>
		</npc>
		
		<npc id="20755">
			<spawn heading="43726" respawn="80" x="39055" y="109986" z="-1384"/>
			<spawn heading="34289" respawn="80" x="39967" y="109075" z="-1080"/>
			<spawn heading="50306" respawn="80" x="41283" y="110555" z="-728"/>
			<spawn heading="3507" respawn="80" x="41776" y="114505" z="-1832"/>
			<spawn heading="58509" respawn="80" x="41844" y="107667" z="-808"/>
			<spawn heading="1722" respawn="80" x="41867" y="112541" z="-1144"/>
			<spawn heading="39046" respawn="80" x="41921" y="112584" z="-1160"/>
			<spawn heading="24709" respawn="80" x="42106" y="107609" z="-880"/>
			<spawn heading="56909" respawn="80" x="43460" y="107307" z="-1232"/>
			<spawn heading="52884" respawn="80" x="44945" y="105737" z="-1024"/>
			<spawn heading="34569" respawn="80" x="45190" y="106446" z="-864"/>
			<spawn heading="50579" respawn="80" x="46937" y="105618" z="-1128"/>
			<spawn heading="22924" respawn="80" x="47111" y="106797" z="-976"/>
			<spawn heading="52688" respawn="80" x="47124" y="107113" z="-1104"/>
			<spawn heading="59720" respawn="80" x="47221" y="108608" z="-2008"/>
			<spawn heading="13951" respawn="80" x="48199" y="107993" z="-1472"/>
			<spawn heading="59281" respawn="80" x="48568" y="108460" z="-1520"/>
			<spawn heading="0" respawn="80" x="49919" y="103523" z="-1120"/>
			<spawn heading="5093" respawn="80" x="50188" y="108101" z="-1072"/>
			<spawn heading="0" respawn="80" x="50896" y="106461" z="-1152"/>
			<spawn heading="57008" respawn="80" x="50974" y="109162" z="-1448"/>
			<spawn heading="36949" respawn="80" x="51708" y="106207" z="-1584"/>
			<spawn heading="30874" respawn="80" x="51815" y="104364" z="-904"/>
			<spawn heading="0" respawn="80" x="51956" y="106021" z="-1568"/>
		</npc>
		
		<npc id="20756">
			<spawn heading="0" x="39032" y="109999" z="-1392"/>
			<spawn heading="22326" x="39967" y="109224" z="-1072"/>
			<spawn heading="0" x="41176" y="110449" z="-680"/>
			<spawn heading="55711" x="41717" y="112541" z="-1128"/>
			<spawn heading="0" x="41823" y="114469" z="-1816"/>
			<spawn heading="0" x="41844" y="107816" z="-776"/>
			<spawn heading="0" x="42071" y="112584" z="-1152"/>
			<spawn heading="0" x="42211" y="107502" z="-904"/>
			<spawn heading="0" x="43354" y="107413" z="-1224"/>
			<spawn heading="43048" x="44810" y="105707" z="-1080"/>
			<spawn heading="41442" x="45397" y="106408" z="-816"/>
			<spawn heading="2785" x="46962" y="105756" z="-1120"/>
			<spawn heading="0" x="47018" y="107219" z="-1072"/>
			<spawn heading="35235" x="47188" y="108729" z="-2000"/>
			<spawn heading="55352" x="47242" y="106549" z="-960"/>
			<spawn heading="0" x="48304" y="107886" z="-1400"/>
			<spawn heading="0" x="48431" y="108403" z="-1496"/>
			<spawn heading="0" x="49813" y="103629" z="-1112"/>
			<spawn heading="37941" x="50188" y="108250" z="-1064"/>
			<spawn heading="0" x="50868" y="109268" z="-1408"/>
			<spawn heading="0" x="51002" y="106567" z="-1496"/>
			<spawn heading="5990" x="51776" y="106277" z="-1584"/>
			<spawn heading="0" x="51920" y="104257" z="-840"/>
			<spawn heading="0" x="52062" y="106127" z="-1576"/>
		</npc>
		
		<npc id="20757">
			<spawn heading="45963" x="39105" y="110053" z="-1360"/>
			<spawn heading="21385" x="40073" y="109181" z="-1080"/>
			<spawn heading="0" x="41190" y="110570" z="-752"/>
			<spawn heading="1722" x="41717" y="112541" z="-1128"/>
			<spawn heading="32771" x="41775" y="114458" z="-1808"/>
			<spawn heading="38395" x="41867" y="107626" z="-824"/>
			<spawn heading="0" x="42027" y="112690" z="-1184"/>
			<spawn heading="53989" x="42106" y="107758" z="-880"/>
			<spawn heading="5462" x="43507" y="107307" z="-1232"/>
			<spawn heading="40047" x="44921" y="105696" z="-1032"/>
			<spawn heading="24873" x="45366" y="106587" z="-832"/>
			<spawn heading="212" x="46918" y="105650" z="-1128"/>
			<spawn heading="49157" x="47124" y="107262" z="-1136"/>
			<spawn heading="42406" x="47244" y="108648" z="-2008"/>
			<spawn heading="16782" x="47289" y="106400" z="-992"/>
			<spawn heading="0" x="48198" y="107843" z="-1432"/>
			<spawn heading="43577" x="48470" y="108499" z="-1544"/>
			<spawn heading="48763" x="49919" y="103569" z="-1112"/>
			<spawn heading="0" x="50294" y="108207" z="-1064"/>
			<spawn heading="0" x="50896" y="106461" z="-1152"/>
			<spawn heading="8028" x="50997" y="109202" z="-1448"/>
			<spawn heading="45170" x="51858" y="106207" z="-1584"/>
			<spawn heading="10875" x="51921" y="104470" z="-912"/>
			<spawn heading="0" x="52106" y="106021" z="-1560"/>
		</npc>
		
		<npc id="21802">
			<spawn heading="0" x="40803" y="117728" z="-1672"/>
			<spawn heading="0" x="42879" y="114141" z="-1608"/>
			<spawn heading="0" x="52485" y="122027" z="-3048"/>
			<spawn heading="0" x="53480" y="114125" z="-2056"/>
		</npc>
		
		<npc id="21803">
			<spawn heading="0" x="44068" y="117670" z="-2008"/>
			<spawn heading="0" x="44437" y="104876" z="-1440"/>
			<spawn heading="0" x="49201" y="113457" z="-1632"/>
			<spawn heading="0" x="53393" y="105071" z="-952"/>
			<spawn heading="0" x="53613" y="115135" z="-1712"/>
			<spawn heading="0" x="54213" y="109010" z="-1216"/>
			<spawn heading="0" x="55756" y="111851" z="-1360"/>
			<spawn heading="0" x="56409" y="108383" z="-1344"/>
		</npc>
		
		<npc id="21804">
			<spawn heading="0" x="40867" y="102357" z="-1192"/>
			<spawn heading="0" x="41072" y="109816" z="-584"/>
			<spawn heading="0" x="56769" y="105782" z="-1488"/>
			<spawn heading="0" x="57352" y="112020" z="-1768"/>
		</npc>
		
		<npc id="30596">
			<spawn heading="61440" x="43996" y="108998" z="-2032"/>
		</npc>
		
		<npc id="30751">
			<spawn heading="0" x="62008" y="107589" z="-1893"/>
		</npc>
		
		<npc id="30752">
			<spawn heading="0" x="64001" y="126486" z="-2016"/>
		</npc>
		
		<npc id="31096">
			<spawn heading="16500" x="45248" y="124352" z="-5411"/>
		</npc>
		
		<npc id="31104">
			<spawn heading="49000" x="45280" y="123504" z="-5409"/>
		</npc>
		
		<npc id="31496">
			<spawn heading="0" x="44953" y="123778" z="-5408"/>
		</npc>
		
		<npc id="35382">
			<spawn heading="0" x="50343" y="111282" z="-1976"/>
		</npc>
		
		<npc id="35383">
			<spawn heading="0" x="43129" y="108841" z="-1984"/>
		</npc>
	</spawns>
</list>