<?xml version="1.0" encoding="UTF-8"?>
<list xmlns:xsi="http://www.w3.org/2001/XMLSchema-instance"
      xsi:noNamespaceSchemaLocation="../../../../../xsd/skillTrees.xsd">
    <skillTree name="palusKnight" classId="32" parentClassId="31" type="classSkillTree">
        <skill minLevel="20" name="Sword/Blunt Weapon Mastery" skillId="217" skillLvl="1" sp="4700"/>
        <skill minLevel="20" name="Heavy Armor Mastery" skillId="232" skillLvl="1" sp="1500"/>
        <skill minLevel="20" name="Heavy Armor Mastery" skillId="232" skillLvl="2" sp="1500"/>
        <skill minLevel="20" name="Heavy Armor Mastery" skillId="232" skillLvl="3" sp="1500"/>
        <skill minLevel="20" name="M. Def." skillId="147" skillLvl="1" sp="2300"/>
        <skill minLevel="20" name="M. Def." skillId="147" skillLvl="2" sp="2300"/>
        <skill minLevel="20" name="Drain Health" skillId="70" skillLvl="3" sp="2300"/>
        <skill minLevel="20" name="Drain Health" skillId="70" skillLvl="4" sp="2300"/>
        <skill minLevel="20" name="Defense Aura" skillId="91" skillLvl="2" sp="4700"/>
        <skill minLevel="20" name="Shield Mastery" skillId="153" skillLvl="1" sp="4700"/>
        <skill minLevel="20" name="Ultimate Defense" skillId="110" skillLvl="1" sp="4700"/>
        <skill minLevel="20" name="Poison" skillId="129" skillLvl="1" sp="4700"/>
        <skill minLevel="24" name="Sword/Blunt Weapon Mastery" skillId="217" skillLvl="2" sp="8800"/>
        <skill minLevel="24" name="Heavy Armor Mastery" skillId="232" skillLvl="4" sp="2900"/>
        <skill minLevel="24" name="Heavy Armor Mastery" skillId="232" skillLvl="5" sp="2900"/>
        <skill minLevel="24" name="Heavy Armor Mastery" skillId="232" skillLvl="6" sp="2900"/>
        <skill minLevel="24" name="M. Def." skillId="147" skillLvl="3" sp="2900"/>
        <skill minLevel="24" name="M. Def." skillId="147" skillLvl="4" sp="2900"/>
        <skill minLevel="24" name="M. Def." skillId="147" skillLvl="5" sp="2900"/>
        <skill minLevel="24" name="Drain Health" skillId="70" skillLvl="5" sp="2900"/>
        <skill minLevel="24" name="Drain Health" skillId="70" skillLvl="6" sp="2900"/>
        <skill minLevel="24" name="Drain Health" skillId="70" skillLvl="7" sp="2900"/>
        <skill minLevel="24" name="Aggression" skillId="28" skillLvl="1" sp="2900"/>
        <skill minLevel="24" name="Aggression" skillId="28" skillLvl="2" sp="2900"/>
        <skill minLevel="24" name="Aggression" skillId="28" skillLvl="3" sp="2900"/>
        <skill minLevel="24" name="Sting" skillId="223" skillLvl="1" sp="2900"/>
        <skill minLevel="24" name="Sting" skillId="223" skillLvl="2" sp="2900"/>
        <skill minLevel="24" name="Sting" skillId="223" skillLvl="3" sp="2900"/>
        <skill minLevel="24" name="Deflect Arrow" skillId="112" skillLvl="1" sp="8800"/>
        <skill minLevel="24" name="Confusion" skillId="2" skillLvl="1" sp="8800"/>
        <skill minLevel="28" name="Sword/Blunt Weapon Mastery" skillId="217" skillLvl="3" sp="6700"/>
        <skill minLevel="28" name="Sword/Blunt Weapon Mastery" skillId="217" skillLvl="4" sp="6700"/>
        <skill minLevel="28" name="Heavy Armor Mastery" skillId="232" skillLvl="7" sp="4400"/>
        <skill minLevel="28" name="Heavy Armor Mastery" skillId="232" skillLvl="8" sp="4400"/>
        <skill minLevel="28" name="Heavy Armor Mastery" skillId="232" skillLvl="9" sp="4400"/>
        <skill minLevel="28" name="M. Def." skillId="147" skillLvl="6" sp="4400"/>
        <skill minLevel="28" name="M. Def." skillId="147" skillLvl="7" sp="4400"/>
        <skill minLevel="28" name="M. Def." skillId="147" skillLvl="8" sp="4400"/>
        <skill minLevel="28" name="Drain Health" skillId="70" skillLvl="8" sp="4400"/>
        <skill minLevel="28" name="Drain Health" skillId="70" skillLvl="9" sp="4400"/>
        <skill minLevel="28" name="Drain Health" skillId="70" skillLvl="10" sp="4400"/>
        <skill minLevel="28" name="Aggression" skillId="28" skillLvl="4" sp="4400"/>
        <skill minLevel="28" name="Aggression" skillId="28" skillLvl="5" sp="4400"/>
        <skill minLevel="28" name="Aggression" skillId="28" skillLvl="6" sp="4400"/>
        <skill minLevel="28" name="Sting" skillId="223" skillLvl="4" sp="4400"/>
        <skill minLevel="28" name="Sting" skillId="223" skillLvl="5" sp="4400"/>
        <skill minLevel="28" name="Sting" skillId="223" skillLvl="6" sp="4400"/>
        <skill minLevel="28" name="Shield Mastery" skillId="153" skillLvl="2" sp="13000"/>
        <skill minLevel="28" name="Confusion" skillId="2" skillLvl="2" sp="13000"/>
        <skill minLevel="28" name="Attack Aura" skillId="77" skillLvl="2" sp="13000"/>
        <skill minLevel="32" name="Sword/Blunt Weapon Mastery" skillId="217" skillLvl="5" sp="11000"/>
        <skill minLevel="32" name="Sword/Blunt Weapon Mastery" skillId="217" skillLvl="6" sp="11000"/>
        <skill minLevel="32" name="Heavy Armor Mastery" skillId="232" skillLvl="10" sp="7400"/>
        <skill minLevel="32" name="Heavy Armor Mastery" skillId="232" skillLvl="11" sp="7400"/>
        <skill minLevel="32" name="Heavy Armor Mastery" skillId="232" skillLvl="12" sp="7400"/>
        <skill minLevel="32" name="M. Def." skillId="147" skillLvl="9" sp="7400"/>
        <skill minLevel="32" name="M. Def." skillId="147" skillLvl="10" sp="7400"/>
        <skill minLevel="32" name="M. Def." skillId="147" skillLvl="11" sp="7400"/>
        <skill minLevel="32" name="Drain Health" skillId="70" skillLvl="11" sp="7400"/>
        <skill minLevel="32" name="Drain Health" skillId="70" skillLvl="12" sp="7400"/>
        <skill minLevel="32" name="Drain Health" skillId="70" skillLvl="13" sp="7400"/>
        <skill minLevel="32" name="Aggression" skillId="28" skillLvl="7" sp="7400"/>
        <skill minLevel="32" name="Aggression" skillId="28" skillLvl="8" sp="7400"/>
        <skill minLevel="32" name="Aggression" skillId="28" skillLvl="9" sp="7400"/>
        <skill minLevel="32" name="Sting" skillId="223" skillLvl="7" sp="7400"/>
        <skill minLevel="32" name="Sting" skillId="223" skillLvl="8" sp="7400"/>
        <skill minLevel="32" name="Sting" skillId="223" skillLvl="9" sp="7400"/>
        <skill minLevel="32" name="Deflect Arrow" skillId="112" skillLvl="2" sp="22000"/>
        <skill minLevel="32" name="Confusion" skillId="2" skillLvl="3" sp="22000"/>
        <skill minLevel="32" name="Power Break" skillId="115" skillLvl="1" sp="22000"/>
        <skill minLevel="36" name="Sword/Blunt Weapon Mastery" skillId="217" skillLvl="7" sp="14000"/>
        <skill minLevel="36" name="Sword/Blunt Weapon Mastery" skillId="217" skillLvl="8" sp="14000"/>
        <skill minLevel="36" name="Heavy Armor Mastery" skillId="232" skillLvl="13" sp="9000"/>
        <skill minLevel="36" name="Heavy Armor Mastery" skillId="232" skillLvl="14" sp="9000"/>
        <skill minLevel="36" name="Heavy Armor Mastery" skillId="232" skillLvl="15" sp="9000"/>
        <skill minLevel="36" name="M. Def." skillId="147" skillLvl="12" sp="9000"/>
        <skill minLevel="36" name="M. Def." skillId="147" skillLvl="13" sp="9000"/>
        <skill minLevel="36" name="M. Def." skillId="147" skillLvl="14" sp="9000"/>
        <skill minLevel="36" name="Drain Health" skillId="70" skillLvl="14" sp="9000"/>
        <skill minLevel="36" name="Drain Health" skillId="70" skillLvl="15" sp="9000"/>
        <skill minLevel="36" name="Drain Health" skillId="70" skillLvl="16" sp="9000"/>
        <skill minLevel="36" name="Aggression" skillId="28" skillLvl="10" sp="9000"/>
        <skill minLevel="36" name="Aggression" skillId="28" skillLvl="11" sp="9000"/>
        <skill minLevel="36" name="Aggression" skillId="28" skillLvl="12" sp="9000"/>
        <skill minLevel="36" name="Sting" skillId="223" skillLvl="10" sp="9000"/>
        <skill minLevel="36" name="Sting" skillId="223" skillLvl="11" sp="9000"/>
        <skill minLevel="36" name="Sting" skillId="223" skillLvl="12" sp="9000"/>
        <skill minLevel="36" name="Freezing Strike" skillId="105" skillLvl="1" sp="14000"/>
        <skill minLevel="36" name="Freezing Strike" skillId="105" skillLvl="2" sp="14000"/>
        <skill minLevel="36" name="Focus Mind" skillId="191" skillLvl="1" sp="28000"/>
        <skill minLevel="36" name="Confusion" skillId="2" skillLvl="4" sp="28000"/>
        <skill minLevel="36" name="Power Break" skillId="115" skillLvl="2" sp="28000"/>
    </skillTree>
</list>
