<?xml version="1.0" encoding="UTF-8" standalone="no"?>
<list>
	<item id="21500" name="Упаковка: Шляпа Кота Кая - (Ивент)" type="EtcItem">
		<set name="icon" val="BranchSys.icon.br_four_leaf_clover_box_i00"/>
		<set name="material" val="steel"/>
		<set name="is_tradable" val="false"/>
		<set name="is_dropable" val="false"/>
		<set name="is_destroyable" val="false"/>
		<set name="is_stackable" val="true"/>
		<set name="is_freightable" val="true"/>
	</item>
	<item id="21501" name="Шляпа Кота Кая - (7 дней)" type="Armor">
		<set name="icon" val="icon.accessory_chi_the_cat_cap_i00"/>
		<set name="default_action" val="equip"/>
		<set name="bodypart" val="hairall"/>
		<set name="material" val="wood"/>
		<set name="weight" val="10"/>
		<set name="is_tradable" val="false"/>
		<set name="is_dropable" val="false"/>
		<set name="time" val="10080"/>
	</item>
	<item id="21502" name="Шляпа Кота Кая - (7 дней (ивент))" type="Armor">
		<set name="icon" val="icon.accessory_chi_the_cat_cap_i00"/>
		<set name="default_action" val="equip"/>
		<set name="bodypart" val="hairall"/>
		<set name="material" val="wood"/>
		<set name="weight" val="10"/>
		<set name="is_tradable" val="false"/>
		<set name="is_dropable" val="false"/>
		<set name="is_destroyable" val="false"/>
		<set name="time" val="10080"/>
	</item>
	<item id="21503" name="Шляпа Кота Кая - (30 дней)" type="Armor">
		<set name="icon" val="icon.accessory_chi_the_cat_cap_i00"/>
		<set name="default_action" val="equip"/>
		<set name="bodypart" val="hairall"/>
		<set name="material" val="wood"/>
		<set name="weight" val="10"/>
		<set name="is_tradable" val="false"/>
		<set name="is_dropable" val="false"/>
		<set name="time" val="43200"/>
	</item>
	<item id="21504" name="Шляпа Кота Кая - (30 дней (ивент))" type="Armor">
		<set name="icon" val="icon.accessory_chi_the_cat_cap_i00"/>
		<set name="default_action" val="equip"/>
		<set name="bodypart" val="hairall"/>
		<set name="material" val="wood"/>
		<set name="weight" val="10"/>
		<set name="is_tradable" val="false"/>
		<set name="is_dropable" val="false"/>
		<set name="is_destroyable" val="false"/>
		<set name="time" val="43200"/>
	</item>
	<item id="21505" name="Шляпа Кота Кая" type="Armor">
		<set name="icon" val="icon.accessory_chi_the_cat_cap_i00"/>
		<set name="default_action" val="equip"/>
		<set name="bodypart" val="hairall"/>
		<set name="material" val="wood"/>
		<set name="weight" val="10"/>
		<set name="is_tradable" val="false"/>
		<set name="is_dropable" val="false"/>
		<set name="is_freightable" val="true"/>
	</item>
	<item id="21506" name="Шляпа Кота Кая - (Ивент)" type="Armor">
		<set name="icon" val="icon.accessory_chi_the_cat_cap_i00"/>
		<set name="default_action" val="equip"/>
		<set name="bodypart" val="hairall"/>
		<set name="material" val="wood"/>
		<set name="weight" val="10"/>
		<set name="is_tradable" val="false"/>
		<set name="is_dropable" val="false"/>
		<set name="is_destroyable" val="false"/>
		<set name="is_freightable" val="true"/>
	</item>
	<item id="21507" name="Упаковка: Шляпа Королевы Кошек (7 дн.)" type="EtcItem">
		<set name="icon" val="BranchSys.icon.br_four_leaf_clover_box_i00"/>
		<set name="material" val="steel"/>
		<set name="is_tradable" val="false"/>
		<set name="is_dropable" val="false"/>
		<set name="is_stackable" val="true"/>
		<set name="is_freightable" val="true"/>
	</item>
	<item id="21508" name="Упаковка: Шляпа Королевы Кошек (7 дн.) - (Ивент)" type="EtcItem">
		<set name="icon" val="BranchSys.icon.br_four_leaf_clover_box_i00"/>
		<set name="material" val="steel"/>
		<set name="is_tradable" val="false"/>
		<set name="is_dropable" val="false"/>
		<set name="is_destroyable" val="false"/>
		<set name="is_stackable" val="true"/>
		<set name="is_freightable" val="true"/>
	</item>
	<item id="21509" name="Упаковка: Шляпа Королевы Кошек (30 дн.)" type="EtcItem">
		<set name="icon" val="BranchSys.icon.br_four_leaf_clover_box_i00"/>
		<set name="material" val="steel"/>
		<set name="is_tradable" val="false"/>
		<set name="is_dropable" val="false"/>
		<set name="is_stackable" val="true"/>
		<set name="is_freightable" val="true"/>
	</item>
	<item id="21510" name="Упаковка: Шляпа Королевы Кошек (30 дн.) - (Ивент)" type="EtcItem">
		<set name="icon" val="BranchSys.icon.br_four_leaf_clover_box_i00"/>
		<set name="material" val="steel"/>
		<set name="is_tradable" val="false"/>
		<set name="is_dropable" val="false"/>
		<set name="is_destroyable" val="false"/>
		<set name="is_stackable" val="true"/>
		<set name="is_freightable" val="true"/>
	</item>
	<item id="21511" name="Упаковка: Шляпа Королевы Кошек" type="EtcItem">
		<set name="icon" val="BranchSys.icon.br_four_leaf_clover_box_i00"/>
		<set name="material" val="steel"/>
		<set name="is_tradable" val="false"/>
		<set name="is_dropable" val="false"/>
		<set name="is_stackable" val="true"/>
		<set name="is_freightable" val="true"/>
	</item>
	<item id="21512" name="Упаковка: Шляпа Королевы Кошек - (Ивент)" type="EtcItem">
		<set name="icon" val="BranchSys.icon.br_four_leaf_clover_box_i00"/>
		<set name="material" val="steel"/>
		<set name="is_tradable" val="false"/>
		<set name="is_dropable" val="false"/>
		<set name="is_destroyable" val="false"/>
		<set name="is_stackable" val="true"/>
		<set name="is_freightable" val="true"/>
	</item>
	<item id="21513" name="Шляпа Королевы Кошек - (7 дней)" type="Armor">
		<set name="icon" val="icon.accessory_queen_of_cat_cap_i00"/>
		<set name="default_action" val="equip"/>
		<set name="bodypart" val="hairall"/>
		<set name="material" val="wood"/>
		<set name="weight" val="10"/>
		<set name="is_tradable" val="false"/>
		<set name="is_dropable" val="false"/>
		<set name="time" val="10080"/>
	</item>
	<item id="21514" name="Шляпа Королевы Кошек - (7 дней (ивент))" type="Armor">
		<set name="icon" val="icon.accessory_queen_of_cat_cap_i00"/>
		<set name="default_action" val="equip"/>
		<set name="bodypart" val="hairall"/>
		<set name="material" val="wood"/>
		<set name="weight" val="10"/>
		<set name="is_tradable" val="false"/>
		<set name="is_dropable" val="false"/>
		<set name="is_destroyable" val="false"/>
		<set name="time" val="10080"/>
	</item>
	<item id="21515" name="Шляпа Королевы Кошек - (30 дней)" type="Armor">
		<set name="icon" val="icon.accessory_queen_of_cat_cap_i00"/>
		<set name="default_action" val="equip"/>
		<set name="bodypart" val="hairall"/>
		<set name="material" val="wood"/>
		<set name="weight" val="10"/>
		<set name="is_tradable" val="false"/>
		<set name="is_dropable" val="false"/>
		<set name="time" val="43200"/>
	</item>
	<item id="21516" name="Шляпа Королевы Кошек - (30 дней (ивент))" type="Armor">
		<set name="icon" val="icon.accessory_queen_of_cat_cap_i00"/>
		<set name="default_action" val="equip"/>
		<set name="bodypart" val="hairall"/>
		<set name="material" val="wood"/>
		<set name="weight" val="10"/>
		<set name="is_tradable" val="false"/>
		<set name="is_dropable" val="false"/>
		<set name="is_destroyable" val="false"/>
		<set name="time" val="43200"/>
	</item>
	<item id="21517" name="Шляпа Королевы Кошек" type="Armor">
		<set name="icon" val="icon.accessory_queen_of_cat_cap_i00"/>
		<set name="default_action" val="equip"/>
		<set name="bodypart" val="hairall"/>
		<set name="material" val="wood"/>
		<set name="weight" val="10"/>
		<set name="is_tradable" val="false"/>
		<set name="is_dropable" val="false"/>
		<set name="is_freightable" val="true"/>
	</item>
	<item id="21518" name="Шляпа Королевы Кошек - (Ивент)" type="Armor">
		<set name="icon" val="icon.accessory_queen_of_cat_cap_i00"/>
		<set name="default_action" val="equip"/>
		<set name="bodypart" val="hairall"/>
		<set name="material" val="wood"/>
		<set name="weight" val="10"/>
		<set name="is_tradable" val="false"/>
		<set name="is_dropable" val="false"/>
		<set name="is_destroyable" val="false"/>
		<set name="is_freightable" val="true"/>
	</item>
	<item id="21519" name="Упаковка: Шляпа Короля Кошек (7 дн.)" type="EtcItem">
		<set name="icon" val="BranchSys.icon.br_four_leaf_clover_box_i00"/>
		<set name="material" val="steel"/>
		<set name="is_tradable" val="false"/>
		<set name="is_dropable" val="false"/>
		<set name="is_stackable" val="true"/>
		<set name="is_freightable" val="true"/>
	</item>
	<item id="21520" name="Упаковка: Шляпа Короля Кошек (7 дн.) - (Ивент)" type="EtcItem">
		<set name="icon" val="BranchSys.icon.br_four_leaf_clover_box_i00"/>
		<set name="material" val="steel"/>
		<set name="is_tradable" val="false"/>
		<set name="is_dropable" val="false"/>
		<set name="is_destroyable" val="false"/>
		<set name="is_stackable" val="true"/>
		<set name="is_freightable" val="true"/>
	</item>
	<item id="21521" name="Упаковка: Шляпа Короля Кошек (30 дн.)" type="EtcItem">
		<set name="icon" val="BranchSys.icon.br_four_leaf_clover_box_i00"/>
		<set name="material" val="steel"/>
		<set name="is_tradable" val="false"/>
		<set name="is_dropable" val="false"/>
		<set name="is_stackable" val="true"/>
		<set name="is_freightable" val="true"/>
	</item>
	<item id="21522" name="Упаковка: Шляпа Короля Кошек (30 дн.) - (Ивент)" type="EtcItem">
		<set name="icon" val="BranchSys.icon.br_four_leaf_clover_box_i00"/>
		<set name="material" val="steel"/>
		<set name="is_tradable" val="false"/>
		<set name="is_dropable" val="false"/>
		<set name="is_destroyable" val="false"/>
		<set name="is_stackable" val="true"/>
		<set name="is_freightable" val="true"/>
	</item>
	<item id="21523" name="Упаковка: Шляпа Короля Кошек" type="EtcItem">
		<set name="icon" val="BranchSys.icon.br_four_leaf_clover_box_i00"/>
		<set name="material" val="steel"/>
		<set name="is_tradable" val="false"/>
		<set name="is_dropable" val="false"/>
		<set name="is_stackable" val="true"/>
		<set name="is_freightable" val="true"/>
	</item>
	<item id="21524" name="Упаковка: Шляпа Короля Кошек - (Ивент)" type="EtcItem">
		<set name="icon" val="BranchSys.icon.br_four_leaf_clover_box_i00"/>
		<set name="material" val="steel"/>
		<set name="is_tradable" val="false"/>
		<set name="is_dropable" val="false"/>
		<set name="is_destroyable" val="false"/>
		<set name="is_stackable" val="true"/>
		<set name="is_freightable" val="true"/>
	</item>
	<item id="21525" name="Шляпа Короля Кошек - (7 дней)" type="Armor">
		<set name="icon" val="icon.accessory_king_of_cat_cap_i00"/>
		<set name="default_action" val="equip"/>
		<set name="bodypart" val="hairall"/>
		<set name="material" val="wood"/>
		<set name="weight" val="10"/>
		<set name="is_tradable" val="false"/>
		<set name="is_dropable" val="false"/>
		<set name="time" val="10080"/>
	</item>
	<item id="21526" name="Шляпа Короля Кошек - (7 дней (ивент))" type="Armor">
		<set name="icon" val="icon.accessory_king_of_cat_cap_i00"/>
		<set name="default_action" val="equip"/>
		<set name="bodypart" val="hairall"/>
		<set name="material" val="wood"/>
		<set name="weight" val="10"/>
		<set name="is_tradable" val="false"/>
		<set name="is_dropable" val="false"/>
		<set name="is_destroyable" val="false"/>
		<set name="time" val="10080"/>
	</item>
	<item id="21527" name="Шляпа Короля Кошек - (30 дней)" type="Armor">
		<set name="icon" val="icon.accessory_king_of_cat_cap_i00"/>
		<set name="default_action" val="equip"/>
		<set name="bodypart" val="hairall"/>
		<set name="material" val="wood"/>
		<set name="weight" val="10"/>
		<set name="is_tradable" val="false"/>
		<set name="is_dropable" val="false"/>
		<set name="time" val="43200"/>
	</item>
	<item id="21528" name="Шляпа Короля Кошек - (30 дней (ивент))" type="Armor">
		<set name="icon" val="icon.accessory_king_of_cat_cap_i00"/>
		<set name="default_action" val="equip"/>
		<set name="bodypart" val="hairall"/>
		<set name="material" val="wood"/>
		<set name="weight" val="10"/>
		<set name="is_tradable" val="false"/>
		<set name="is_dropable" val="false"/>
		<set name="is_destroyable" val="false"/>
		<set name="time" val="43200"/>
	</item>
	<item id="21529" name="Шляпа Короля Кошек" type="Armor">
		<set name="icon" val="icon.accessory_king_of_cat_cap_i00"/>
		<set name="default_action" val="equip"/>
		<set name="bodypart" val="hairall"/>
		<set name="material" val="wood"/>
		<set name="weight" val="10"/>
		<set name="is_tradable" val="false"/>
		<set name="is_dropable" val="false"/>
		<set name="is_freightable" val="true"/>
	</item>
	<item id="21530" name="Шляпа Короля Кошек - (Ивент)" type="Armor">
		<set name="icon" val="icon.accessory_king_of_cat_cap_i00"/>
		<set name="default_action" val="equip"/>
		<set name="bodypart" val="hairall"/>
		<set name="material" val="wood"/>
		<set name="weight" val="10"/>
		<set name="is_tradable" val="false"/>
		<set name="is_dropable" val="false"/>
		<set name="is_destroyable" val="false"/>
		<set name="is_freightable" val="true"/>
	</item>
	<item id="21531" name="Упаковка: Бантик (7 дн.)" type="EtcItem">
		<set name="icon" val="BranchSys.icon.br_four_leaf_clover_box_i00"/>
		<set name="material" val="steel"/>
		<set name="is_tradable" val="false"/>
		<set name="is_dropable" val="false"/>
		<set name="is_stackable" val="true"/>
		<set name="is_freightable" val="true"/>
	</item>
	<item id="21532" name="Упаковка: Бантик (7 дн.) - (Ивент)" type="EtcItem">
		<set name="icon" val="BranchSys.icon.br_four_leaf_clover_box_i00"/>
		<set name="material" val="steel"/>
		<set name="is_tradable" val="false"/>
		<set name="is_dropable" val="false"/>
		<set name="is_destroyable" val="false"/>
		<set name="is_stackable" val="true"/>
		<set name="is_freightable" val="true"/>
	</item>
	<item id="21533" name="Упаковка: Бантик (30 дн.)" type="EtcItem">
		<set name="icon" val="BranchSys.icon.br_four_leaf_clover_box_i00"/>
		<set name="material" val="steel"/>
		<set name="is_tradable" val="false"/>
		<set name="is_dropable" val="false"/>
		<set name="is_stackable" val="true"/>
		<set name="is_freightable" val="true"/>
	</item>
	<item id="21534" name="Упаковка: Бантик (30 дн.) - (Ивент)" type="EtcItem">
		<set name="icon" val="BranchSys.icon.br_four_leaf_clover_box_i00"/>
		<set name="material" val="steel"/>
		<set name="is_tradable" val="false"/>
		<set name="is_dropable" val="false"/>
		<set name="is_destroyable" val="false"/>
		<set name="is_stackable" val="true"/>
		<set name="is_freightable" val="true"/>
	</item>
	<item id="21535" name="Упаковка: Бантик" type="EtcItem">
		<set name="icon" val="BranchSys.icon.br_four_leaf_clover_box_i00"/>
		<set name="material" val="steel"/>
		<set name="is_tradable" val="false"/>
		<set name="is_dropable" val="false"/>
		<set name="is_stackable" val="true"/>
		<set name="is_freightable" val="true"/>
	</item>
	<item id="21536" name="Упаковка: Бантик - (Ивент)" type="EtcItem">
		<set name="icon" val="BranchSys.icon.br_four_leaf_clover_box_i00"/>
		<set name="material" val="steel"/>
		<set name="is_tradable" val="false"/>
		<set name="is_dropable" val="false"/>
		<set name="is_destroyable" val="false"/>
		<set name="is_stackable" val="true"/>
		<set name="is_freightable" val="true"/>
	</item>
	<item id="21537" name="Бантик - (7 дней)" type="Armor">
		<set name="icon" val="icon.accessory_ev_ribbon_band_i00"/>
		<set name="default_action" val="equip"/>
		<set name="bodypart" val="hairall"/>
		<set name="material" val="wood"/>
		<set name="weight" val="10"/>
		<set name="is_tradable" val="false"/>
		<set name="is_dropable" val="false"/>
		<set name="time" val="10080"/>
		<cond msgId="1518">
			<player sex="0"/>
		</cond>
	</item>
	<item id="21538" name="Бантик - (7 дней (ивент))" type="Armor">
		<set name="icon" val="icon.accessory_ev_ribbon_band_i00"/>
		<set name="default_action" val="equip"/>
		<set name="bodypart" val="hairall"/>
		<set name="material" val="wood"/>
		<set name="weight" val="10"/>
		<set name="is_tradable" val="false"/>
		<set name="is_dropable" val="false"/>
		<set name="is_destroyable" val="false"/>
		<set name="time" val="10080"/>
		<cond msgId="1518">
			<player sex="0"/>
		</cond>
	</item>
	<item id="21539" name="Бантик - (30 дней)" type="Armor">
		<set name="icon" val="icon.accessory_ev_ribbon_band_i00"/>
		<set name="default_action" val="equip"/>
		<set name="bodypart" val="hairall"/>
		<set name="material" val="wood"/>
		<set name="weight" val="10"/>
		<set name="is_tradable" val="false"/>
		<set name="is_dropable" val="false"/>
		<set name="time" val="43200"/>
		<cond msgId="1518">
			<player sex="0"/>
		</cond>
	</item>
	<item id="21540" name="Бантик - (30 дней (ивент))" type="Armor">
		<set name="icon" val="icon.accessory_ev_ribbon_band_i00"/>
		<set name="default_action" val="equip"/>
		<set name="bodypart" val="hairall"/>
		<set name="material" val="wood"/>
		<set name="weight" val="10"/>
		<set name="is_tradable" val="false"/>
		<set name="is_dropable" val="false"/>
		<set name="is_destroyable" val="false"/>
		<set name="time" val="43200"/>
		<cond msgId="1518">
			<player sex="0"/>
		</cond>
	</item>
	<item id="21541" name="Бантик" type="Armor">
		<set name="icon" val="icon.accessory_ev_ribbon_band_i00"/>
		<set name="default_action" val="equip"/>
		<set name="bodypart" val="hairall"/>
		<set name="material" val="wood"/>
		<set name="weight" val="10"/>
		<set name="is_tradable" val="false"/>
		<set name="is_dropable" val="false"/>
		<set name="is_freightable" val="true"/>
		<cond msgId="1518">
			<player sex="0"/>
		</cond>
	</item>
	<item id="21542" name="Бантик - (Ивент)" type="Armor">
		<set name="icon" val="icon.accessory_ev_ribbon_band_i00"/>
		<set name="default_action" val="equip"/>
		<set name="bodypart" val="hairall"/>
		<set name="material" val="wood"/>
		<set name="weight" val="10"/>
		<set name="is_tradable" val="false"/>
		<set name="is_dropable" val="false"/>
		<set name="is_destroyable" val="false"/>
		<set name="is_freightable" val="true"/>
		<cond msgId="1518">
			<player sex="0"/>
		</cond>
	</item>
	<item id="21543" name="Упаковка: Элегантная Шляпа (7 дн.)" type="EtcItem">
		<set name="icon" val="BranchSys.icon.br_four_leaf_clover_box_i00"/>
		<set name="material" val="steel"/>
		<set name="is_tradable" val="false"/>
		<set name="is_dropable" val="false"/>
		<set name="is_stackable" val="true"/>
		<set name="is_freightable" val="true"/>
	</item>
	<item id="21544" name="Упаковка: Элегантная Шляпа (7 дн.) - (Ивент)" type="EtcItem">
		<set name="icon" val="BranchSys.icon.br_four_leaf_clover_box_i00"/>
		<set name="material" val="steel"/>
		<set name="is_tradable" val="false"/>
		<set name="is_dropable" val="false"/>
		<set name="is_destroyable" val="false"/>
		<set name="is_stackable" val="true"/>
		<set name="is_freightable" val="true"/>
	</item>
	<item id="21545" name="Упаковка: Элегантная Шляпа (30 дн.)" type="EtcItem">
		<set name="icon" val="BranchSys.icon.br_four_leaf_clover_box_i00"/>
		<set name="material" val="steel"/>
		<set name="is_tradable" val="false"/>
		<set name="is_dropable" val="false"/>
		<set name="is_stackable" val="true"/>
		<set name="is_freightable" val="true"/>
	</item>
	<item id="21546" name="Упаковка: Элегантная Шляпа (30 дн.) - (Ивент)" type="EtcItem">
		<set name="icon" val="BranchSys.icon.br_four_leaf_clover_box_i00"/>
		<set name="material" val="steel"/>
		<set name="is_tradable" val="false"/>
		<set name="is_dropable" val="false"/>
		<set name="is_destroyable" val="false"/>
		<set name="is_stackable" val="true"/>
		<set name="is_freightable" val="true"/>
	</item>
	<item id="21547" name="Упаковка: Элегантная Шляпа" type="EtcItem">
		<set name="icon" val="BranchSys.icon.br_four_leaf_clover_box_i00"/>
		<set name="material" val="steel"/>
		<set name="is_tradable" val="false"/>
		<set name="is_dropable" val="false"/>
		<set name="is_stackable" val="true"/>
		<set name="is_freightable" val="true"/>
	</item>
	<item id="21548" name="Упаковка: Элегантная Шляпа - (Ивент)" type="EtcItem">
		<set name="icon" val="BranchSys.icon.br_four_leaf_clover_box_i00"/>
		<set name="material" val="steel"/>
		<set name="is_tradable" val="false"/>
		<set name="is_dropable" val="false"/>
		<set name="is_destroyable" val="false"/>
		<set name="is_stackable" val="true"/>
		<set name="is_freightable" val="true"/>
	</item>
	<item id="21549" name="Элегантная Шляпа - (7 дней)" type="Armor">
		<set name="icon" val="icon.accessory_dandy_cap2_i00"/>
		<set name="default_action" val="equip"/>
		<set name="bodypart" val="hairall"/>
		<set name="material" val="wood"/>
		<set name="weight" val="10"/>
		<set name="is_tradable" val="false"/>
		<set name="is_dropable" val="false"/>
		<set name="time" val="10080"/>
	</item>
	<item id="21550" name="Элегантная Шляпа - (7 дней (ивент))" type="Armor">
		<set name="icon" val="icon.accessory_dandy_cap2_i00"/>
		<set name="default_action" val="equip"/>
		<set name="bodypart" val="hairall"/>
		<set name="material" val="wood"/>
		<set name="weight" val="10"/>
		<set name="is_tradable" val="false"/>
		<set name="is_dropable" val="false"/>
		<set name="is_destroyable" val="false"/>
		<set name="time" val="10080"/>
	</item>
	<item id="21551" name="Элегантная Шляпа - (30 дней)" type="Armor">
		<set name="icon" val="icon.accessory_dandy_cap2_i00"/>
		<set name="default_action" val="equip"/>
		<set name="bodypart" val="hairall"/>
		<set name="material" val="wood"/>
		<set name="weight" val="10"/>
		<set name="is_tradable" val="false"/>
		<set name="is_dropable" val="false"/>
		<set name="time" val="43200"/>
	</item>
	<item id="21552" name="Элегантная Шляпа - (30 дней (ивент))" type="Armor">
		<set name="icon" val="icon.accessory_dandy_cap2_i00"/>
		<set name="default_action" val="equip"/>
		<set name="bodypart" val="hairall"/>
		<set name="material" val="wood"/>
		<set name="weight" val="10"/>
		<set name="is_tradable" val="false"/>
		<set name="is_dropable" val="false"/>
		<set name="is_destroyable" val="false"/>
		<set name="time" val="43200"/>
	</item>
	<item id="21553" name="Элегантная Шляпа" type="Armor">
		<set name="icon" val="icon.accessory_dandy_cap2_i00"/>
		<set name="default_action" val="equip"/>
		<set name="bodypart" val="hairall"/>
		<set name="material" val="wood"/>
		<set name="weight" val="10"/>
		<set name="is_tradable" val="false"/>
		<set name="is_dropable" val="false"/>
		<set name="is_freightable" val="true"/>
	</item>
	<item id="21554" name="Элегантная Шляпа - (Ивент)" type="Armor">
		<set name="icon" val="icon.accessory_dandy_cap2_i00"/>
		<set name="default_action" val="equip"/>
		<set name="bodypart" val="hairall"/>
		<set name="material" val="wood"/>
		<set name="weight" val="10"/>
		<set name="is_tradable" val="false"/>
		<set name="is_dropable" val="false"/>
		<set name="is_destroyable" val="false"/>
		<set name="is_freightable" val="true"/>
	</item>
	<item id="21555" name="Упаковка: Диадема Валькирии (7 дн.)" type="EtcItem">
		<set name="icon" val="BranchSys.icon.br_four_leaf_clover_box_i00"/>
		<set name="material" val="steel"/>
		<set name="is_tradable" val="false"/>
		<set name="is_dropable" val="false"/>
		<set name="is_stackable" val="true"/>
		<set name="is_freightable" val="true"/>
	</item>
	<item id="21556" name="Упаковка: Диадема Валькирии (7 дн.) - (Ивент)" type="EtcItem">
		<set name="icon" val="BranchSys.icon.br_four_leaf_clover_box_i00"/>
		<set name="material" val="steel"/>
		<set name="is_tradable" val="false"/>
		<set name="is_dropable" val="false"/>
		<set name="is_destroyable" val="false"/>
		<set name="is_stackable" val="true"/>
		<set name="is_freightable" val="true"/>
	</item>
	<item id="21557" name="Упаковка: Диадема Валькирии (30 дн.)" type="EtcItem">
		<set name="icon" val="BranchSys.icon.br_four_leaf_clover_box_i00"/>
		<set name="material" val="steel"/>
		<set name="is_tradable" val="false"/>
		<set name="is_dropable" val="false"/>
		<set name="is_stackable" val="true"/>
		<set name="is_freightable" val="true"/>
	</item>
	<item id="21558" name="Упаковка: Диадема Валькирии (30 дн.) - (Ивент)" type="EtcItem">
		<set name="icon" val="BranchSys.icon.br_four_leaf_clover_box_i00"/>
		<set name="material" val="steel"/>
		<set name="is_tradable" val="false"/>
		<set name="is_dropable" val="false"/>
		<set name="is_destroyable" val="false"/>
		<set name="is_stackable" val="true"/>
		<set name="is_freightable" val="true"/>
	</item>
	<item id="21559" name="Упаковка: Диадема Валькирии" type="EtcItem">
		<set name="icon" val="BranchSys.icon.br_four_leaf_clover_box_i00"/>
		<set name="material" val="steel"/>
		<set name="is_tradable" val="false"/>
		<set name="is_dropable" val="false"/>
		<set name="is_stackable" val="true"/>
		<set name="is_freightable" val="true"/>
	</item>
	<item id="21560" name="Упаковка: Диадема Валькирии - (Ивент)" type="EtcItem">
		<set name="icon" val="BranchSys.icon.br_four_leaf_clover_box_i00"/>
		<set name="material" val="steel"/>
		<set name="is_tradable" val="false"/>
		<set name="is_dropable" val="false"/>
		<set name="is_destroyable" val="false"/>
		<set name="is_stackable" val="true"/>
		<set name="is_freightable" val="true"/>
	</item>
	<item id="21561" name="Диадема Валькирии - (7 дней)" type="Armor">
		<set name="icon" val="BranchSys.icon.br_valkyrie_cap_i00"/>
		<set name="default_action" val="equip"/>
		<set name="bodypart" val="hairall"/>
		<set name="material" val="wood"/>
		<set name="weight" val="10"/>
		<set name="is_tradable" val="false"/>
		<set name="is_dropable" val="false"/>
		<set name="time" val="10080"/>
	</item>
	<item id="21562" name="Диадема Валькирии - (7 дней (ивент))" type="Armor">
		<set name="icon" val="BranchSys.icon.br_valkyrie_cap_i00"/>
		<set name="default_action" val="equip"/>
		<set name="bodypart" val="hairall"/>
		<set name="material" val="wood"/>
		<set name="weight" val="10"/>
		<set name="is_tradable" val="false"/>
		<set name="is_dropable" val="false"/>
		<set name="is_destroyable" val="false"/>
		<set name="time" val="10080"/>
	</item>
	<item id="21563" name="Диадема Валькирии - (30 дней)" type="Armor">
		<set name="icon" val="BranchSys.icon.br_valkyrie_cap_i00"/>
		<set name="default_action" val="equip"/>
		<set name="bodypart" val="hairall"/>
		<set name="material" val="wood"/>
		<set name="weight" val="10"/>
		<set name="is_tradable" val="false"/>
		<set name="is_dropable" val="false"/>
		<set name="time" val="43200"/>
	</item>
	<item id="21564" name="Диадема Валькирии - (30 дней (ивент))" type="Armor">
		<set name="icon" val="BranchSys.icon.br_valkyrie_cap_i00"/>
		<set name="default_action" val="equip"/>
		<set name="bodypart" val="hairall"/>
		<set name="material" val="wood"/>
		<set name="weight" val="10"/>
		<set name="is_tradable" val="false"/>
		<set name="is_dropable" val="false"/>
		<set name="is_destroyable" val="false"/>
		<set name="time" val="43200"/>
	</item>
	<item id="21565" name="Диадема Валькирии" type="Armor">
		<set name="icon" val="BranchSys.icon.br_valkyrie_cap_i00"/>
		<set name="default_action" val="equip"/>
		<set name="bodypart" val="hairall"/>
		<set name="material" val="wood"/>
		<set name="weight" val="10"/>
		<set name="is_tradable" val="false"/>
		<set name="is_dropable" val="false"/>
		<set name="is_freightable" val="true"/>
	</item>
	<item id="21566" name="Диадема Валькирии - (Ивент)" type="Armor">
		<set name="icon" val="BranchSys.icon.br_valkyrie_cap_i00"/>
		<set name="default_action" val="equip"/>
		<set name="bodypart" val="hairall"/>
		<set name="material" val="wood"/>
		<set name="weight" val="10"/>
		<set name="is_tradable" val="false"/>
		<set name="is_dropable" val="false"/>
		<set name="is_destroyable" val="false"/>
		<set name="is_freightable" val="true"/>
	</item>
	<item id="21567" name="Упаковка: Пластиковый Парик (7 дн.)" type="EtcItem">
		<set name="icon" val="BranchSys.icon.br_four_leaf_clover_box_i00"/>
		<set name="material" val="steel"/>
		<set name="is_tradable" val="false"/>
		<set name="is_dropable" val="false"/>
		<set name="is_stackable" val="true"/>
		<set name="is_freightable" val="true"/>
	</item>
	<item id="21568" name="Упаковка: Пластиковый Парик (7 дн.) - (Ивент)" type="EtcItem">
		<set name="icon" val="BranchSys.icon.br_four_leaf_clover_box_i00"/>
		<set name="material" val="steel"/>
		<set name="is_tradable" val="false"/>
		<set name="is_dropable" val="false"/>
		<set name="is_destroyable" val="false"/>
		<set name="is_stackable" val="true"/>
		<set name="is_freightable" val="true"/>
	</item>
	<item id="21569" name="Упаковка: Пластиковый Парик (30 дн.)" type="EtcItem">
		<set name="icon" val="BranchSys.icon.br_four_leaf_clover_box_i00"/>
		<set name="material" val="steel"/>
		<set name="is_tradable" val="false"/>
		<set name="is_dropable" val="false"/>
		<set name="is_stackable" val="true"/>
		<set name="is_freightable" val="true"/>
	</item>
	<item id="21570" name="Упаковка: Пластиковый Парик (30 дн.) - (Ивент)" type="EtcItem">
		<set name="icon" val="BranchSys.icon.br_four_leaf_clover_box_i00"/>
		<set name="material" val="steel"/>
		<set name="is_tradable" val="false"/>
		<set name="is_dropable" val="false"/>
		<set name="is_destroyable" val="false"/>
		<set name="is_stackable" val="true"/>
		<set name="is_freightable" val="true"/>
	</item>
	<item id="21571" name="Упаковка: Пластиковый Парик" type="EtcItem">
		<set name="icon" val="BranchSys.icon.br_four_leaf_clover_box_i00"/>
		<set name="material" val="steel"/>
		<set name="is_tradable" val="false"/>
		<set name="is_dropable" val="false"/>
		<set name="is_stackable" val="true"/>
		<set name="is_freightable" val="true"/>
	</item>
	<item id="21572" name="Упаковка: Пластиковый Парик - (Ивент)" type="EtcItem">
		<set name="icon" val="BranchSys.icon.br_four_leaf_clover_box_i00"/>
		<set name="material" val="steel"/>
		<set name="is_tradable" val="false"/>
		<set name="is_dropable" val="false"/>
		<set name="is_destroyable" val="false"/>
		<set name="is_stackable" val="true"/>
		<set name="is_freightable" val="true"/>
	</item>
	<item id="21573" name="Пластиковый Парик - (7 дней)" type="Armor">
		<set name="icon" val="BranchSys.icon.br_plastic_hair_f_i00"/>
		<set name="default_action" val="equip"/>
		<set name="bodypart" val="hairall"/>
		<set name="material" val="wood"/>
		<set name="weight" val="10"/>
		<set name="is_tradable" val="false"/>
		<set name="is_dropable" val="false"/>
		<set name="time" val="10080"/>
	</item>
	<item id="21574" name="Пластиковый Парик - (7 дней (ивент))" type="Armor">
		<set name="icon" val="BranchSys.icon.br_plastic_hair_f_i00"/>
		<set name="default_action" val="equip"/>
		<set name="bodypart" val="hairall"/>
		<set name="material" val="wood"/>
		<set name="weight" val="10"/>
		<set name="is_tradable" val="false"/>
		<set name="is_dropable" val="false"/>
		<set name="is_destroyable" val="false"/>
		<set name="time" val="10080"/>
	</item>
	<item id="21575" name="Пластиковый Парик - (30 дней)" type="Armor">
		<set name="icon" val="BranchSys.icon.br_plastic_hair_f_i00"/>
		<set name="default_action" val="equip"/>
		<set name="bodypart" val="hairall"/>
		<set name="material" val="wood"/>
		<set name="weight" val="10"/>
		<set name="is_tradable" val="false"/>
		<set name="is_dropable" val="false"/>
		<set name="time" val="43200"/>
	</item>
	<item id="21576" name="Пластиковый Парик - (30 дней (ивент))" type="Armor">
		<set name="icon" val="BranchSys.icon.br_plastic_hair_f_i00"/>
		<set name="default_action" val="equip"/>
		<set name="bodypart" val="hairall"/>
		<set name="material" val="wood"/>
		<set name="weight" val="10"/>
		<set name="is_tradable" val="false"/>
		<set name="is_dropable" val="false"/>
		<set name="is_destroyable" val="false"/>
		<set name="time" val="43200"/>
	</item>
	<item id="21577" name="Пластиковый Парик" type="Armor">
		<set name="icon" val="BranchSys.icon.br_plastic_hair_f_i00"/>
		<set name="default_action" val="equip"/>
		<set name="bodypart" val="hairall"/>
		<set name="material" val="wood"/>
		<set name="weight" val="10"/>
		<set name="is_tradable" val="false"/>
		<set name="is_dropable" val="false"/>
		<set name="is_freightable" val="true"/>
	</item>
	<item id="21578" name="Пластиковый Парик - (Ивент)" type="Armor">
		<set name="icon" val="BranchSys.icon.br_plastic_hair_f_i00"/>
		<set name="default_action" val="equip"/>
		<set name="bodypart" val="hairall"/>
		<set name="material" val="wood"/>
		<set name="weight" val="10"/>
		<set name="is_tradable" val="false"/>
		<set name="is_dropable" val="false"/>
		<set name="is_destroyable" val="false"/>
		<set name="is_freightable" val="true"/>
	</item>
	<item id="21579" name="Сфера Сэрома: Ранг S84" type="EtcItem">
		<set name="icon" val="BranchSys2.icon.etc_warding_orb_gold_i00"/>
		<set name="material" val="paper"/>
		<set name="weight" val="20"/>
		<set name="is_stackable" val="true"/>
	</item>
	<item id="21580" name="Футболка Ольфа" type="Armor">
		<set name="icon" val="BranchSys2.icon.7anni_shirt_i00"/>
		<set name="default_action" val="equip"/>
		<set name="bodypart" val="underwear"/>
		<set name="material" val="crystal"/>
		<set name="weight" val="130"/>
		<set name="is_tradable" val="false"/>
		<set name="is_dropable" val="false"/>
		<set name="is_freightable" val="true"/>
		<set name="enchant_enabled" val="true"/>
		<enchant_options>
			<level val="4">
				<option id="24975"/>
				<!--CON +1-->
			</level>
			<level val="5">
				<option id="24976"/>
				<!--CON +1 and MEN +1-->
				<option id="24981"/>
				<!--Passive Skill: Moving speed increases by 7.-->
			</level>
			<level val="6">
				<option id="24977"/>
				<!--INT +1, STR +1, CON +1, MEN +1-->
				<option id="24981"/>
				<!--Passive Skill: Moving speed increases by 7.-->
			</level>
			<level val="7">
				<option id="24978"/>
				<!--INT +1, STR +1, CON +1, MEN +1-->
				<option id="24981"/>
				<!--Passive Skill: Moving speed increases by 7.-->
				<option id="24982"/>
				<!--Active Skil: Blessed Escape ability can be used. C\nan be used every 20 hour(s).-->
			</level>
			<level val="8">
				<option id="24979"/>
				<!--STR +1, DEX +1, CON +1, INT +1, WIT +1, MEN +1-->
				<option id="24981"/>
				<!--Passive Skill: Moving speed increases by 7.-->
				<option id="24982"/>
				<!--Active Skil: Blessed Escape ability can be used. C\nan be used every 20 hour(s).-->
			</level>
			<level val="9">
				<option id="24980"/>
				<!--STR +1, DEX +1, CON +2, INT +1, WIT +1, MEN +2-->
				<option id="24981"/>
				<!--Passive Skill: Moving speed increases by 7.-->
				<option id="24983"/>
				<!--Active Skil: Temporarily becomes invincible for 7 \nseconds. Can be used every 20 hour(s).-->
			</level>
			<level val="10">
				<option id="24985"/>
				<!--STR +2, DEX +1, CON +2, INT +2, WIT +1, MEN +2-->
				<option id="24983"/>
				<!--Active Skil: Temporarily becomes invincible for 7 \nseconds. Can be used every 20 hour(s).-->
				<option id="24984"/>
				<!--Increases M. Def by 18 and Speed by 7. Increases physical skill damage by 93. Decreases MP Consumption by 3%. Increases Critical Damage by 41.3, and Magical Crintical Rate by 2.-->
			</level>
		</enchant_options>
		<for>
			<add order="0x10" stat="pDef" val="28"/>
		</for>
	</item>
	<item id="21581" name="Свиток: Модифицировать Футболку Ольфа" type="EtcItem">
		<set name="icon" val="BranchSys2.icon.etc_scroll_of_enchant_shirt_i01"/>
		<set name="default_action" val="skill_reduce"/>
		<set name="etcitem_type" val="scrl_enchant_am"/>
		<set name="immediate_effect" val="1"/>
		<set name="material" val="paper"/>
		<set name="weight" val="120"/>
		<set name="price" val="302272"/>
		<set name="is_dropable" val="false"/>
		<set name="is_stackable" val="true"/>
		<set name="is_oly_restricted" val="true"/>
		<set name="handler" val="EnchantScrolls"/>
		<set name="item_skill" val="22247-1"/>
	</item>
	<item id="21582" name="Благословенный Свиток: Модифицировать Футболку Ольфа" type="EtcItem">
		<set name="icon" val="BranchSys2.icon.etc_scroll_of_enchant_shirt_i01"/>
		<set name="default_action" val="skill_reduce"/>
		<set name="etcitem_type" val="scrl_enchant_am"/>
		<set name="immediate_effect" val="1"/>
		<set name="material" val="paper"/>
		<set name="weight" val="120"/>
		<set name="price" val="0"/>
		<set name="is_dropable" val="false"/>
		<set name="is_stackable" val="true"/>
		<set name="is_oly_restricted" val="true"/>
		<set name="handler" val="EnchantScrolls"/>
		<set name="item_skill" val="22248-1"/>
	</item>
	<item id="21583" name="Праздничный Плащ - Черный" type="Armor">
		<set name="icon" val="BranchSys2.Icon.7anni_cloack_i00"/>
		<set name="default_action" val="equip"/>
		<set name="bodypart" val="back"/>
		<set name="material" val="cloth"/>
		<set name="weight" val="220"/>
		<set name="is_tradable" val="false"/>
		<set name="is_dropable" val="false"/>
		<set name="is_destroyable" val="false"/>
		<cond msgId="2453">
			<player cloakStatus="1"/>
		</cond>
		<for>
			<add order="0x10" stat="pDef" val="25"/>
		</for>
	</item>
	<item id="21584" name="Упаковка: Праздничный Плащ - Черный" type="EtcItem">
		<set name="icon" val="BranchSys.icon.br_four_leaf_clover_box_i00"/>
		<set name="material" val="steel"/>
		<set name="is_tradable" val="false"/>
		<set name="is_dropable" val="false"/>
		<set name="is_stackable" val="true"/>
		<set name="is_freightable" val="true"/>
	</item>
	<item id="21585" name="Праздничный Плащ - Черный - (Ивент)" type="Armor">
		<set name="icon" val="BranchSys2.Icon.7anni_cloack_i00"/>
		<set name="default_action" val="equip"/>
		<set name="bodypart" val="back"/>
		<set name="material" val="cloth"/>
		<set name="weight" val="220"/>
		<set name="is_tradable" val="false"/>
		<set name="is_dropable" val="false"/>
		<set name="is_destroyable" val="false"/>
		<set name="is_freightable" val="true"/>
		<cond msgId="2453">
			<player cloakStatus="1"/>
		</cond>
		<for>
			<add order="0x10" stat="pDef" val="25"/>
		</for>
	</item>
	<item id="21586" name="Упаковка: Праздничный Плащ - Черный - (Ивент)" type="EtcItem">
		<set name="icon" val="BranchSys.icon.br_four_leaf_clover_box_i00"/>
		<set name="material" val="steel"/>
		<set name="is_tradable" val="false"/>
		<set name="is_dropable" val="false"/>
		<set name="is_destroyable" val="false"/>
		<set name="is_stackable" val="true"/>
		<set name="is_freightable" val="true"/>
	</item>
	<item id="21587" name="Праздничный Плащ - Кроваво-Красный" type="Armor">
		<set name="icon" val="BranchSys2.Icon.7anni_cloack_i01"/>
		<set name="default_action" val="equip"/>
		<set name="bodypart" val="back"/>
		<set name="material" val="cloth"/>
		<set name="weight" val="220"/>
		<set name="is_tradable" val="false"/>
		<set name="is_dropable" val="false"/>
		<set name="is_destroyable" val="false"/>
		<cond msgId="2453">
			<player cloakStatus="1"/>
		</cond>
		<for>
			<add order="0x10" stat="pDef" val="25"/>
		</for>
	</item>
	<item id="21588" name="Праздничный Плащ - Белый" type="Armor">
		<set name="icon" val="BranchSys2.Icon.7anni_cloack_i02"/>
		<set name="default_action" val="equip"/>
		<set name="bodypart" val="back"/>
		<set name="material" val="cloth"/>
		<set name="weight" val="220"/>
		<set name="is_tradable" val="false"/>
		<set name="is_dropable" val="false"/>
		<set name="is_destroyable" val="false"/>
		<cond msgId="2453">
			<player cloakStatus="1"/>
		</cond>
		<for>
			<add order="0x10" stat="pDef" val="25"/>
		</for>
	</item>
	<item id="21589" name="Упаковка: Праздничный Плащ - Белый" type="EtcItem">
		<set name="icon" val="BranchSys.icon.br_four_leaf_clover_box_i00"/>
		<set name="material" val="steel"/>
		<set name="is_tradable" val="false"/>
		<set name="is_dropable" val="false"/>
		<set name="is_stackable" val="true"/>
		<set name="is_freightable" val="true"/>
	</item>
	<item id="21590" name="Праздничный Плащ - Белый - (Ивент)" type="Armor">
		<set name="icon" val="BranchSys2.Icon.7anni_cloack_i02"/>
		<set name="default_action" val="equip"/>
		<set name="bodypart" val="back"/>
		<set name="material" val="cloth"/>
		<set name="weight" val="220"/>
		<set name="is_tradable" val="false"/>
		<set name="is_dropable" val="false"/>
		<set name="is_destroyable" val="false"/>
		<set name="is_freightable" val="true"/>
		<cond msgId="2453">
			<player cloakStatus="1"/>
		</cond>
		<for>
			<add order="0x10" stat="pDef" val="25"/>
		</for>
	</item>
	<item id="21591" name="Упаковка: Праздничный Плащ - Белый - (Ивент)" type="EtcItem">
		<set name="icon" val="BranchSys.icon.br_four_leaf_clover_box_i00"/>
		<set name="material" val="steel"/>
		<set name="is_tradable" val="false"/>
		<set name="is_dropable" val="false"/>
		<set name="is_destroyable" val="false"/>
		<set name="is_stackable" val="true"/>
		<set name="is_freightable" val="true"/>
	</item>
	<item id="21592" name="Упаковка: 5 видов Аксессуаров Магической Защиты" type="EtcItem">
		<set name="icon" val="BranchSys.icon.br_four_leaf_clover_box_i00"/>
		<set name="material" val="steel"/>
		<set name="is_tradable" val="false"/>
		<set name="is_dropable" val="false"/>
		<set name="is_destroyable" val="false"/>
		<set name="is_stackable" val="true"/>
		<set name="is_freightable" val="true"/>
	</item>
	<item id="21593" name="Самоцвет Зигго" type="EtcItem">
		<set name="icon" val="icon.etc_jewel_red_i00"/>
		<set name="material" val="crystal"/>
		<set name="is_stackable" val="true"/>
	</item>
	<item id="21594" name="Колпак С Днем Рождения!" type="Armor">
		<set name="icon" val="icon.accessory_birthday_cap_i00"/>
		<set name="default_action" val="equip"/>
		<set name="bodypart" val="hairall"/>
		<set name="material" val="wood"/>
		<set name="weight" val="10"/>
		<set name="is_tradable" val="false"/>
		<set name="is_dropable" val="false"/>
	</item>
	<item id="21595" name="Торт Именинника" type="EtcItem">
		<set name="icon" val="BranchSys.icon.br_birthday_cake_i00"/>
		<set name="default_action" val="skill_reduce"/>
		<set name="etcitem_type" val="potion"/>
		<set name="immediate_effect" val="1"/>
		<set name="material" val="paper"/>
		<set name="weight" val="10"/>
		<set name="is_tradable" val="false"/>
		<set name="is_dropable" val="false"/>
		<set name="is_sellable" val="false"/>
		<set name="is_premium" val="true"/>
		<set name="handler" val="ItemSkills"/>
		<set name="item_skill" val="22249-1"/>
		<cond addName="1" msgId="113">
			<player vehicleMounted="false"/>
		</cond>
	</item>
	<item id="21596" name="Пакет Благословения-100" type="EtcItem">
		<set name="icon" val="icon.etc_pi_gift_box_i04"/>
		<set name="material" val="steel"/>
		<set name="is_tradable" val="false"/>
		<set name="is_dropable" val="false"/>
		<set name="is_stackable" val="true"/>
		<set name="is_freightable" val="true"/>
	</item>
	<item id="21597" name="Пакет Охоты-100" type="EtcItem">
		<set name="icon" val="icon.etc_pi_gift_box_i04"/>
		<set name="material" val="steel"/>
		<set name="is_tradable" val="false"/>
		<set name="is_dropable" val="false"/>
		<set name="is_stackable" val="true"/>
		<set name="is_freightable" val="true"/>
	</item>
	<item id="21598" name="Пакет Благословения-200" type="EtcItem">
		<set name="icon" val="icon.etc_pi_gift_box_i04"/>
		<set name="material" val="steel"/>
		<set name="is_tradable" val="false"/>
		<set name="is_dropable" val="false"/>
		<set name="is_stackable" val="true"/>
		<set name="is_freightable" val="true"/>
	</item>
	<item id="21599" name="Пакет Охоты-200" type="EtcItem">
		<set name="icon" val="icon.etc_pi_gift_box_i04"/>
		<set name="material" val="steel"/>
		<set name="is_tradable" val="false"/>
		<set name="is_dropable" val="false"/>
		<set name="is_stackable" val="true"/>
		<set name="is_freightable" val="true"/>
	</item>
</list>